Workbook

Sheet MAIN
A1: Stress_Scenarios | B1: Short_des | C1: code | D1: Long_des | E1: Unnamed: 6 | F1: Factors1 | G1: TITLE | H1: Factors2 | I1: FACTOR_TAG | J1: Check | K1: Mapping 3 livello | L1: Factor_type | M1: Mapping 2 livello | N1: Mapping 1 Livello | O1: Shock_Value
A2: 1995_MCADJ | B2: Mid-cycle adjustment Mar 1995-Dec 1995 | C2: 2302 | D2: Scenario to capture the mid-cycle adjustment of the 1995, based on historical factor returns during the period Mar1995 to Dec1995. | E2: Tsy 3M USD_3m - Yield: -76.00bps, | F2: Tsy 3M | G2: =+VLOOKUP(F2,[1]Explore!$B:$I,8,0) -> Govt USD | H2: USD_3m | I2: =+VLOOKUP(H2,[1]Explore!$A:$I,9,0) -> Govt USD | J2: =IF(AND(ISNA(G2),ISNA(I2)),"BOTH #N/A","OK") -> OK | K2: =IFERROR(I2, IFERROR(G2, L2)) -> Govt USD | L2: Yield | M2: =_xlfn.IFNA(VLOOKUP(K2,'Mapping DEF'!A:C,2,0),"") -> Curve (Local) | N2: =+_xlfn.IFNA(VLOOKUP(M2,'Mapping DEF'!B:C,2,FALSE),"") -> Term Structure | O2: -76.00bps
A3: 1995_MCADJ | B3: Mid-cycle adjustment Mar 1995-Dec 1995 | C3: 2302 | D3: Scenario to capture the mid-cycle adjustment of the 1995, based on historical factor returns during the period Mar1995 to Dec1995. | E3: Tsy 1Y USD_1yr - Yield: -129.00bps, | F3: Tsy 1Y | G3: =+VLOOKUP(F3,[1]Explore!$B:$I,8,0) -> Govt USD | H3: USD_1yr | I3: =+VLOOKUP(H3,[1]Explore!$A:$I,9,0) -> Govt USD | J3: =IF(AND(ISNA(G3),ISNA(I3)),"BOTH #N/A","OK") -> OK | K3: =IFERROR(I3, IFERROR(G3, L3)) -> Govt USD | L3: Yield | M3: =_xlfn.IFNA(VLOOKUP(K3,'Mapping DEF'!A:C,2,0),"") -> Curve (Local) | N3: =+_xlfn.IFNA(VLOOKUP(M3,'Mapping DEF'!B:C,2,FALSE),"") -> Term Structure | O3: -129.00bps
A4: 1995_MCADJ | B4: Mid-cycle adjustment Mar 1995-Dec 1995 | C4: 2302 | D4: Scenario to capture the mid-cycle adjustment of the 1995, based on historical factor returns during the period Mar1995 to Dec1995. | E4: Tsy 2Y USD_2yr - Yield: -164.00bps, | F4: Tsy 2Y | G4: =+VLOOKUP(F4,[1]Explore!$B:$I,8,0) -> Govt USD | H4: USD_2yr | I4: =+VLOOKUP(H4,[1]Explore!$A:$I,9,0) -> Govt USD | J4: =IF(AND(ISNA(G4),ISNA(I4)),"BOTH #N/A","OK") -> OK | K4: =IFERROR(I4, IFERROR(G4, L4)) -> Govt USD | L4: Yield | M4: =_xlfn.IFNA(VLOOKUP(K4,'Mapping DEF'!A:C,2,0),"") -> Curve (Local) | N4: =+_xlfn.IFNA(VLOOKUP(M4,'Mapping DEF'!B:C,2,FALSE),"") -> Term Structure | O4: -164.00bps
A5: 1995_MCADJ | B5: Mid-cycle adjustment Mar 1995-Dec 1995 | C5: 2302 | D5: Scenario to capture the mid-cycle adjustment of the 1995, based on historical factor returns during the period Mar1995 to Dec1995. | E5: Tsy 5Y USD_5yr - Yield: -169.00bps, | F5: Tsy 5Y | G5: =+VLOOKUP(F5,[1]Explore!$B:$I,8,0) -> Govt USD | H5: USD_5yr | I5: =+VLOOKUP(H5,[1]Explore!$A:$I,9,0) -> Govt USD | J5: =IF(AND(ISNA(G5),ISNA(I5)),"BOTH #N/A","OK") -> OK | K5: =IFERROR(I5, IFERROR(G5, L5)) -> Govt USD | L5: Yield | M5: =_xlfn.IFNA(VLOOKUP(K5,'Mapping DEF'!A:C,2,0),"") -> Curve (Local) | N5: =+_xlfn.IFNA(VLOOKUP(M5,'Mapping DEF'!B:C,2,FALSE),"") -> Term Structure | O5: -169.00bps
A6: 1995_MCADJ | B6: Mid-cycle adjustment Mar 1995-Dec 1995 | C6: 2302 | D6: Scenario to capture the mid-cycle adjustment of the 1995, based on historical factor returns during the period Mar1995 to Dec1995. | E6: Tsy 10Y USD_10yr - Yield: -162.00bps, | F6: Tsy 10Y | G6: =+VLOOKUP(F6,[1]Explore!$B:$I,8,0) -> Govt USD | H6: USD_10yr | I6: =+VLOOKUP(H6,[1]Explore!$A:$I,9,0) -> Govt USD | J6: =IF(AND(ISNA(G6),ISNA(I6)),"BOTH #N/A","OK") -> OK | K6: =IFERROR(I6, IFERROR(G6, L6)) -> Govt USD | L6: Yield | M6: =_xlfn.IFNA(VLOOKUP(K6,'Mapping DEF'!A:C,2,0),"") -> Curve (Local) | N6: =+_xlfn.IFNA(VLOOKUP(M6,'Mapping DEF'!B:C,2,FALSE),"") -> Term Structure | O6: -162.00bps
A7: 1995_MCADJ | B7: Mid-cycle adjustment Mar 1995-Dec 1995 | C7: 2302 | D7: Scenario to capture the mid-cycle adjustment of the 1995, based on historical factor returns during the period Mar1995 to Dec1995. | E7: Tsy 30Y USD_30yr - Yield: -139.00bps, | F7: Tsy 30Y | G7: =+VLOOKUP(F7,[1]Explore!$B:$I,8,0) -> Govt USD | H7: USD_30yr | I7: =+VLOOKUP(H7,[1]Explore!$A:$I,9,0) -> Govt USD | J7: =IF(AND(ISNA(G7),ISNA(I7)),"BOTH #N/A","OK") -> OK | K7: =IFERROR(I7, IFERROR(G7, L7)) -> Govt USD | L7: Yield | M7: =_xlfn.IFNA(VLOOKUP(K7,'Mapping DEF'!A:C,2,0),"") -> Curve (Local) | N7: =+_xlfn.IFNA(VLOOKUP(M7,'Mapping DEF'!B:C,2,FALSE),"") -> Term Structure | O7: -139.00bps
A8: 1995_MCADJ | B8: Mid-cycle adjustment Mar 1995-Dec 1995 | C8: 2302 | D8: Scenario to capture the mid-cycle adjustment of the 1995, based on historical factor returns during the period Mar1995 to Dec1995. | E8: SP500 Consum Discr S5COND - Index Level: 17.00pct, | F8: SP500 Consum Discr | G8: =+VLOOKUP(F8,[1]Explore!$B:$I,8,0) -> Equity Implied Volatility | H8: S5COND | I8: =+VLOOKUP(H8,[1]Explore!$A:$I,9,0) -> Equity Implied Volatility | J8: =IF(AND(ISNA(G8),ISNA(I8)),"BOTH #N/A","OK") -> OK | K8: =IFERROR(I8, IFERROR(G8, L8)) -> Equity Implied Volatility | L8: Index Level | M8: =_xlfn.IFNA(VLOOKUP(K8,'Mapping DEF'!A:C,2,0),"") -> Equity Derivatives | N8: =+_xlfn.IFNA(VLOOKUP(M8,'Mapping DEF'!B:C,2,FALSE),"") -> Equity | O8: 17.00pct
A9: 1995_MCADJ | B9: Mid-cycle adjustment Mar 1995-Dec 1995 | C9: 2302 | D9: Scenario to capture the mid-cycle adjustment of the 1995, based on historical factor returns during the period Mar1995 to Dec1995. | E9: SP500 Consum Stapl S5CONS - Index Level: 24.00pct, | F9: SP500 Consum Stapl | G9: =+VLOOKUP(F9,[1]Explore!$B:$I,8,0) -> Equity Implied Volatility | H9: S5CONS | I9: =+VLOOKUP(H9,[1]Explore!$A:$I,9,0) -> Equity Implied Volatility | J9: =IF(AND(ISNA(G9),ISNA(I9)),"BOTH #N/A","OK") -> OK | K9: =IFERROR(I9, IFERROR(G9, L9)) -> Equity Implied Volatility | L9: Index Level | M9: =_xlfn.IFNA(VLOOKUP(K9,'Mapping DEF'!A:C,2,0),"") -> Equity Derivatives | N9: =+_xlfn.IFNA(VLOOKUP(M9,'Mapping DEF'!B:C,2,FALSE),"") -> Equity | O9: 24.00pct
A10: 1995_MCADJ | B10: Mid-cycle adjustment Mar 1995-Dec 1995 | C10: 2302 | D10: Scenario to capture the mid-cycle adjustment of the 1995, based on historical factor returns during the period Mar1995 to Dec1995. | E10: S&P 500 Energy S5ENRS - Index Level: 29.00pct, | F10: S&P 500 Energy | G10: =+VLOOKUP(F10,[1]Explore!$B:$I,8,0) -> Equity Implied Volatility | H10: S5ENRS | I10: =+VLOOKUP(H10,[1]Explore!$A:$I,9,0) -> Equity Implied Volatility | J10: =IF(AND(ISNA(G10),ISNA(I10)),"BOTH #N/A","OK") -> OK | K10: =IFERROR(I10, IFERROR(G10, L10)) -> Equity Implied Volatility | L10: Index Level | M10: =_xlfn.IFNA(VLOOKUP(K10,'Mapping DEF'!A:C,2,0),"") -> Equity Derivatives | N10: =+_xlfn.IFNA(VLOOKUP(M10,'Mapping DEF'!B:C,2,FALSE),"") -> Equity | O10: 29.00pct
A11: 1995_MCADJ | B11: Mid-cycle adjustment Mar 1995-Dec 1995 | C11: 2302 | D11: Scenario to capture the mid-cycle adjustment of the 1995, based on historical factor returns during the period Mar1995 to Dec1995. | E11: S&P 500 Financials S5FINL - Index Level: 38.00pct, | F11: S&P 500 Financials | G11: =+VLOOKUP(F11,[1]Explore!$B:$I,8,0) -> Equity Implied Volatility | H11: S5FINL | I11: =+VLOOKUP(H11,[1]Explore!$A:$I,9,0) -> Equity Implied Volatility | J11: =IF(AND(ISNA(G11),ISNA(I11)),"BOTH #N/A","OK") -> OK | K11: =IFERROR(I11, IFERROR(G11, L11)) -> Equity Implied Volatility | L11: Index Level | M11: =_xlfn.IFNA(VLOOKUP(K11,'Mapping DEF'!A:C,2,0),"") -> Equity Derivatives | N11: =+_xlfn.IFNA(VLOOKUP(M11,'Mapping DEF'!B:C,2,FALSE),"") -> Equity | O11: 38.00pct
A12: 1995_MCADJ | B12: Mid-cycle adjustment Mar 1995-Dec 1995 | C12: 2302 | D12: Scenario to capture the mid-cycle adjustment of the 1995, based on historical factor returns during the period Mar1995 to Dec1995. | E12: S&P 500 Health Care S5HLTH - Index Level: 33.00pct, | F12: S&P 500 Health Care | G12: =+VLOOKUP(F12,[1]Explore!$B:$I,8,0) -> Equity Implied Volatility | H12: S5HLTH | I12: =+VLOOKUP(H12,[1]Explore!$A:$I,9,0) -> Equity Implied Volatility | J12: =IF(AND(ISNA(G12),ISNA(I12)),"BOTH #N/A","OK") -> OK | K12: =IFERROR(I12, IFERROR(G12, L12)) -> Equity Implied Volatility | L12: Index Level | M12: =_xlfn.IFNA(VLOOKUP(K12,'Mapping DEF'!A:C,2,0),"") -> Equity Derivatives | N12: =+_xlfn.IFNA(VLOOKUP(M12,'Mapping DEF'!B:C,2,FALSE),"") -> Equity | O12: 33.00pct
A13: 1995_MCADJ | B13: Mid-cycle adjustment Mar 1995-Dec 1995 | C13: 2302 | D13: Scenario to capture the mid-cycle adjustment of the 1995, based on historical factor returns during the period Mar1995 to Dec1995. | E13: S&P 500 Industrials S5INDU - Index Level: 26.00pct, | F13: S&P 500 Industrials | G13: =+VLOOKUP(F13,[1]Explore!$B:$I,8,0) -> Equity Implied Volatility | H13: S5INDU | I13: =+VLOOKUP(H13,[1]Explore!$A:$I,9,0) -> Equity Implied Volatility | J13: =IF(AND(ISNA(G13),ISNA(I13)),"BOTH #N/A","OK") -> OK | K13: =IFERROR(I13, IFERROR(G13, L13)) -> Equity Implied Volatility | L13: Index Level | M13: =_xlfn.IFNA(VLOOKUP(K13,'Mapping DEF'!A:C,2,0),"") -> Equity Derivatives | N13: =+_xlfn.IFNA(VLOOKUP(M13,'Mapping DEF'!B:C,2,FALSE),"") -> Equity | O13: 26.00pct
... A22: AICHEV | B22: U.S. Global AI Diffusion: Evasion & Diversion (06/2025) | C22: 2109 | D22: Increased technology flow to allies under the replacement framework enables China and other adversaries to successfully acquire advanced US AI chips through evasion. | E22: Electrical Equipment - Electrical Equipment [FMI_CHNA_INDELECEQ-FMI_NAMR_INDELECEQ] - Industry Return: 10.00pct, | F22: Electrical Equipment | G22: =+VLOOKUP(F22,[1]Explore!$B:$I,8,0) -> Industrials | H22: Equipment | I22: =+VLOOKUP(H22,[1]Explore!$A:$I,9,0) -> #N/A | J22: =IF(AND(ISNA(G22),ISNA(I22)),"BOTH #N/A","OK") -> OK | K22: =IFERROR(I22, IFERROR(G22, L22)) -> Industrials | L22: Industry Return | M22: =_xlfn.IFNA(VLOOKUP(K22,'Mapping DEF'!A:C,2,0),"") -> Industry Allocation | N22: =+_xlfn.IFNA(VLOOKUP(M22,'Mapping DEF'!B:C,2,FALSE),"") -> Equity | O22: 10.00pct
A23: AICHEV | B23: U.S. Global AI Diffusion: Evasion & Diversion (06/2025) | C23: 2109 | D23: Increased technology flow to allies under the replacement framework enables China and other adversaries to successfully acquire advanced US AI chips through evasion. | E23: Semiconductors - Semiconductors & Equipment [FMI_CHNA_ITCSEMICON-FMI_NAMR_ITCSEMICEQ] - Industry Return: 30.00pct, | F23: Semiconductors & Equipment | G23: =+VLOOKUP(F23,[1]Explore!$B:$I,8,0) -> Information Technology | I23: =+VLOOKUP(H23,[1]Explore!$A:$I,9,0) -> #N/A | J23: =IF(AND(ISNA(G23),ISNA(I23)),"BOTH #N/A","OK") -> OK | K23: =IFERROR(I23, IFERROR(G23, L23)) -> Information Technology | L23: Industry Return | M23: =_xlfn.IFNA(VLOOKUP(K23,'Mapping DEF'!A:C,2,0),"") -> Industry Allocation | N23: =+_xlfn.IFNA(VLOOKUP(M23,'Mapping DEF'!B:C,2,FALSE),"") -> Equity | O23: 30.00pct
A24: AICHEV | B24: U.S. Global AI Diffusion: Evasion & Diversion (06/2025) | C24: 2109 | D24: Increased technology flow to allies under the replacement framework enables China and other adversaries to successfully acquire advanced US AI chips through evasion. | E24: US HY Other Technology - US HY Market [USD_HY_TECHOTHR_SF-USD_HY_MARKET_SF] - Spread Yield: 50.00bps | F24: US HY Other Technology | G24: =+VLOOKUP(F24,[1]Explore!$B:$I,8,0) -> Corporate HY USD - Industry | H24: Technology | I24: =+VLOOKUP(H24,[1]Explore!$A:$I,9,0) -> #N/A | J24: =IF(AND(ISNA(G24),ISNA(I24)),"BOTH #N/A","OK") -> OK | K24: =IFERROR(I24, IFERROR(G24, L24)) -> Corporate HY USD - Industry | L24: Spread Yield | M24: =_xlfn.IFNA(VLOOKUP(K24,'Mapping DEF'!A:C,2,0),"") -> Spread | N24: =+_xlfn.IFNA(VLOOKUP(M24,'Mapping DEF'!B:C,2,FALSE),"") -> Spread | O24: 50.00bps
A25: AICHRET | B25: U.S. Global AI Diffusion: China Retaliation (06/2025) | C25: 2108 | D25: In response to the US export restrictions under the replacement framework, China?s retaliatory response involves imposing rare earth export limits to hinder U.S. chip manufacturing. | E25: GSCI PRECIOUS METALS GSPMSPOT - Price Level: 15.00pct, | F25: GSCI PRECIOUS METALS | G25: =+VLOOKUP(F25,[1]Explore!$B:$I,8,0) -> Alternative - Commodity | H25: GSPMSPOT | I25: =+VLOOKUP(H25,[1]Explore!$A:$I,9,0) -> Alternative - Commodity | J25: =IF(AND(ISNA(G25),ISNA(I25)),"BOTH #N/A","OK") -> OK | K25: =IFERROR(I25, IFERROR(G25, L25)) -> Alternative - Commodity | L25: Price Level | M25: =_xlfn.IFNA(VLOOKUP(K25,'Mapping DEF'!A:C,2,0),"") -> Alternative | N25: =+_xlfn.IFNA(VLOOKUP(M25,'Mapping DEF'!B:C,2,FALSE),"") -> Other | O25: 15.00pct
A26: AICHRET | B26: U.S. Global AI Diffusion: China Retaliation (06/2025) | C26: 2108 | D26: In response to the US export restrictions under the replacement framework, China?s retaliatory response involves imposing rare earth export limits to hinder U.S. chip manufacturing. | E26: Alum Div Metals & Mining FMI_NAMR_MATALUDIV - Industry Return: 10.00pct, | F26: Alum Div Metals & Mining | G26: =+VLOOKUP(F26,[1]Explore!$B:$I,8,0) -> #N/A | H26: FMI_NAMR_MATALUDIV | I26: =+VLOOKUP(H26,[1]Explore!$A:$I,9,0) -> #N/A | J26: =IF(AND(ISNA(G26),ISNA(I26)),"BOTH #N/A","OK") -> BOTH #N/A | K26: =IFERROR(I26, IFERROR(G26, L26)) -> Materials | L26: Materials | M26: =_xlfn.IFNA(VLOOKUP(K26,'Mapping DEF'!A:C,2,0),"") -> Industry Allocation | N26: =+_xlfn.IFNA(VLOOKUP(M26,'Mapping DEF'!B:C,2,FALSE),"") -> Equity | O26: 10.00pct
A27: AICHRET | B27: U.S. Global AI Diffusion: China Retaliation (06/2025) | C27: 2108 | D27: In response to the US export restrictions under the replacement framework, China?s retaliatory response involves imposing rare earth export limits to hinder U.S. chip manufacturing. | E27: Electrical Equipment FMI_NAMR_INDELECEQ - Industry Return: -15.00pct, | F27: Electrical Equipment | G27: =+VLOOKUP(F27,[1]Explore!$B:$I,8,0) -> Industrials | H27: FMI_NAMR_INDELECEQ | I27: =+VLOOKUP(H27,[1]Explore!$A:$I,9,0) -> #N/A | J27: =IF(AND(ISNA(G27),ISNA(I27)),"BOTH #N/A","OK") -> OK | K27: =IFERROR(I27, IFERROR(G27, L27)) -> Industrials | L27: Industry Return | M27: =_xlfn.IFNA(VLOOKUP(K27,'Mapping DEF'!A:C,2,0),"") -> Industry Allocation | N27: =+_xlfn.IFNA(VLOOKUP(M27,'Mapping DEF'!B:C,2,FALSE),"") -> Equity | O27: -15.00pct
A28: AICHRET | B28: U.S. Global AI Diffusion: China Retaliation (06/2025) | C28: 2108 | D28: In response to the US export restrictions under the replacement framework, China?s retaliatory response involves imposing rare earth export limits to hinder U.S. chip manufacturing. | E28: Software & Internet Services FMI_CHNA_ITCSOFTNET - Industry Return: 10.00pct, | F28: Software & Internet Services | G28: =+VLOOKUP(F28,[1]Explore!$B:$I,8,0) -> #N/A | H28: FMI_CHNA_ITCSOFTNET | I28: =+VLOOKUP(H28,[1]Explore!$A:$I,9,0) -> #N/A | J28: =IF(AND(ISNA(G28),ISNA(I28)),"BOTH #N/A","OK") -> BOTH #N/A | K28: =IFERROR(I28, IFERROR(G28, L28)) -> Information Technology | L28: Information Technology | M28: =_xlfn.IFNA(VLOOKUP(K28,'Mapping DEF'!A:C,2,0),"") -> Industry Allocation | N28: =+_xlfn.IFNA(VLOOKUP(M28,'Mapping DEF'!B:C,2,FALSE),"") -> Equity | O28: 10.00pct
A29: AICHRET | B29: U.S. Global AI Diffusion: China Retaliation (06/2025) | C29: 2108 | D29: In response to the US export restrictions under the replacement framework, China?s retaliatory response involves imposing rare earth export limits to hinder U.S. chip manufacturing. | E29: US HY Tech Hardware - US HY Market [USD_HY_HARDWARE_SF-USD_HY_MARKET_SF] - Spread Yield: 100.00bps | F29: US HY Tech Hardware | G29: =+VLOOKUP(F29,[1]Explore!$B:$I,8,0) -> Corporate HY USD - Industry | H29: Hardware | I29: =+VLOOKUP(H29,[1]Explore!$A:$I,9,0) -> #N/A | J29: =IF(AND(ISNA(G29),ISNA(I29)),"BOTH #N/A","OK") -> OK | K29: =IFERROR(I29, IFERROR(G29, L29)) -> Corporate HY USD - Industry | L29: Spread Yield | M29: =_xlfn.IFNA(VLOOKUP(K29,'Mapping DEF'!A:C,2,0),"") -> Spread | N29: =+_xlfn.IFNA(VLOOKUP(M29,'Mapping DEF'!B:C,2,FALSE),"") -> Spread | O29: 100.00bps
A30: AITWNBL | B30: U.S. Global AI Diffusion: China Blockade on Taiwan (06/2025) | C30: 2107 | D30: As an ultimatum to the AI war, China imposes a blockade of Taiwan, forcing it to stop chip exports to the US, causing the largest major supply chain disruption the US semiconductor industry has ever experienced. | E30: Tsy 5Y USD_5yr - Yield: 100.00bps, | F30: Tsy 5Y | G30: =+VLOOKUP(F30,[1]Explore!$B:$I,8,0) -> Govt USD | H30: USD_5yr | I30: =+VLOOKUP(H30,[1]Explore!$A:$I,9,0) -> Govt USD | J30: =IF(AND(ISNA(G30),ISNA(I30)),"BOTH #N/A","OK") -> OK | K30: =IFERROR(I30, IFERROR(G30, L30)) -> Govt USD | L30: Yield | M30: =_xlfn.IFNA(VLOOKUP(K30,'Mapping DEF'!A:C,2,0),"") -> Curve (Local) | N30: =+_xlfn.IFNA(VLOOKUP(M30,'Mapping DEF'!B:C,2,FALSE),"") -> Term Structure | O30: 100.00bps
A31: AITWNBL | B31: U.S. Global AI Diffusion: China Blockade on Taiwan (06/2025) | C31: 2107 | D31: As an ultimatum to the AI war, China imposes a blockade of Taiwan, forcing it to stop chip exports to the US, causing the largest major supply chain disruption the US semiconductor industry has ever experienced. | E31: GSCI PRECIOUS METALS GSPMSPOT - Price Level: -10.00pct, | F31: GSCI PRECIOUS METALS | G31: =+VLOOKUP(F31,[1]Explore!$B:$I,8,0) -> Alternative - Commodity | H31: GSPMSPOT | I31: =+VLOOKUP(H31,[1]Explore!$A:$I,9,0) -> Alternative - Commodity | J31: =IF(AND(ISNA(G31),ISNA(I31)),"BOTH #N/A","OK") -> OK | K31: =IFERROR(I31, IFERROR(G31, L31)) -> Alternative - Commodity | L31: Price Level | M31: =_xlfn.IFNA(VLOOKUP(K31,'Mapping DEF'!A:C,2,0),"") -> Alternative | N31: =+_xlfn.IFNA(VLOOKUP(M31,'Mapping DEF'!B:C,2,FALSE),"") -> Other | O31: -10.00pct
A32: AITWNBL | B32: U.S. Global AI Diffusion: China Blockade on Taiwan (06/2025) | C32: 2107 | D32: As an ultimatum to the AI war, China imposes a blockade of Taiwan, forcing it to stop chip exports to the US, causing the largest major supply chain disruption the US semiconductor industry has ever experienced. | E32: CNY/USD CNY_FX_USD - FX: 5.00pct, | F32: CNYUSD | G32: =+VLOOKUP(F32,[1]Explore!$B:$I,8,0) -> #N/A | H32: CNY_FX_USD | I32: =+VLOOKUP(H32,[1]Explore!$A:$I,9,0) -> Emerging Currency | J32: =IF(AND(ISNA(G32),ISNA(I32)),"BOTH #N/A","OK") -> OK | K32: =IFERROR(I32, IFERROR(G32, L32)) -> Emerging Currency | L32: FX | M32: =_xlfn.IFNA(VLOOKUP(K32,'Mapping DEF'!A:C,2,0),"") -> FX | N32: =+_xlfn.IFNA(VLOOKUP(M32,'Mapping DEF'!B:C,2,FALSE),"") -> FX | O32: 5.00pct
A33: AITWNBL | B33: U.S. Global AI Diffusion: China Blockade on Taiwan (06/2025) | C33: 2107 | D33: As an ultimatum to the AI war, China imposes a blockade of Taiwan, forcing it to stop chip exports to the US, causing the largest major supply chain disruption the US semiconductor industry has ever experienced. | E33: Taiwan TWSE TWSE - Index Level: -30.00pct, | F33: Taiwan TWSE | G33: =+VLOOKUP(F33,[1]Explore!$B:$I,8,0) -> Equity Implied Volatility | H33: TWSE | I33: =+VLOOKUP(H33,[1]Explore!$A:$I,9,0) -> Equity Implied Volatility | J33: =IF(AND(ISNA(G33),ISNA(I33)),"BOTH #N/A","OK") -> OK | K33: =IFERROR(I33, IFERROR(G33, L33)) -> Equity Implied Volatility | L33: Index Level | M33: =_xlfn.IFNA(VLOOKUP(K33,'Mapping DEF'!A:C,2,0),"") -> Equity Derivatives | N33: =+_xlfn.IFNA(VLOOKUP(M33,'Mapping DEF'!B:C,2,FALSE),"") -> Equity | O33: -30.00pct
A34: AITWNBL | B34: U.S. Global AI Diffusion: China Blockade on Taiwan (06/2025) | C34: 2107 | D34: As an ultimatum to the AI war, China imposes a blockade of Taiwan, forcing it to stop chip exports to the US, causing the largest major supply chain disruption the US semiconductor industry has ever experienced. | E34: Aerospace & Defense FMI_NAMR_INDAIRDEF - Industry Return: 25.00pct, | F34: Aerospace & Defense | G34: =+VLOOKUP(F34,[1]Explore!$B:$I,8,0) -> Industrials | H34: FMI_NAMR_INDAIRDEF | I34: =+VLOOKUP(H34,[1]Explore!$A:$I,9,0) -> #N/A | J34: =IF(AND(ISNA(G34),ISNA(I34)),"BOTH #N/A","OK") -> OK | K34: =IFERROR(I34, IFERROR(G34, L34)) -> Industrials | L34: Industry Return | M34: =_xlfn.IFNA(VLOOKUP(K34,'Mapping DEF'!A:C,2,0),"") -> Industry Allocation | N34: =+_xlfn.IFNA(VLOOKUP(M34,'Mapping DEF'!B:C,2,FALSE),"") -> Equity | O34: 25.00pct
A35: AITWNBL | B35: U.S. Global AI Diffusion: China Blockade on Taiwan (06/2025) | C35: 2107 | D35: As an ultimatum to the AI war, China imposes a blockade of Taiwan, forcing it to stop chip exports to the US, causing the largest major supply chain disruption the US semiconductor industry has ever experienced. | E35: Semiconductors & Equipment FMI_NAMR_ITCSEMICEQ - Industry Return: -35.00pct, | F35: Semiconductors & Equipment | G35: =+VLOOKUP(F35,[1]Explore!$B:$I,8,0) -> Information Technology | H35: FMI_NAMR_ITCSEMICEQ | I35: =+VLOOKUP(H35,[1]Explore!$A:$I,9,0) -> #N/A | J35: =IF(AND(ISNA(G35),ISNA(I35)),"BOTH #N/A","OK") -> OK | K35: =IFERROR(I35, IFERROR(G35, L35)) -> Information Technology | L35: Industry Return | M35: =_xlfn.IFNA(VLOOKUP(K35,'Mapping DEF'!A:C,2,0),"") -> Industry Allocation | N35: =+_xlfn.IFNA(VLOOKUP(M35,'Mapping DEF'!B:C,2,FALSE),"") -> Equity | O35: -35.00pct
... A81: BTAX_COMP | B81: US Corporate Tax Reform - Compromise Plan (07/2021) | C81: 2460 | D81: A dialed down tax reform package passes, but US EU trade tensions rise over digital services taxes. | E81: MSCI EUROPE(EUR) - MSCI World Net TR [MXEU-MSCIWLDNET] - Index Level: -2.00pct | F81: MSCI EUROPE(EUR) | G81: =+VLOOKUP(F81,[1]Explore!$B:$I,8,0) -> Equity Implied Volatility | H81: EUROPEEUR | I81: =+VLOOKUP(H81,[1]Explore!$A:$I,9,0) -> #N/A | J81: =IF(AND(ISNA(G81),ISNA(I81)),"BOTH #N/A","OK") -> OK | K81: =IFERROR(I81, IFERROR(G81, L81)) -> Equity Implied Volatility | L81: Index Level | M81: =_xlfn.IFNA(VLOOKUP(K81,'Mapping DEF'!A:C,2,0),"") -> Equity Derivatives | N81: =+_xlfn.IFNA(VLOOKUP(M81,'Mapping DEF'!B:C,2,FALSE),"") -> Equity | O81: -2.00pct
A82: C07_ABS | B82: Credit '07 - Absolute, Jul 01, 2007 - Jul 01, 2008 | C82: 2308 | D82: Credit & liquidity crisis stemming from a severe slowdown in the housing market causing significant widening of credit spreads and increased implied volatility. Shocks for DxS Factors are spreads. | E82: - | G82: =+VLOOKUP(F82,[1]Explore!$B:$I,8,0) -> #N/A | H82: - | I82: =+VLOOKUP(H82,[1]Explore!$A:$I,9,0) -> #N/A | J82: =IF(AND(ISNA(G82),ISNA(I82)),"BOTH #N/A","OK") -> BOTH #N/A | K82: =IFERROR(I82, IFERROR(G82, L82)) -> - | L82: - | M82: =_xlfn.IFNA(VLOOKUP(K82,'Mapping DEF'!A:C,2,0),"") | N82: =+_xlfn.IFNA(VLOOKUP(M82,'Mapping DEF'!B:C,2,FALSE),"")
A83: C08_REL | B83: Crash '08 - Relative, Sep 12 - Nov 03, 2008 | C83: 2309 | D83: Credit & liquidity crisis and equity market crash set off by Lehman Brothers bankruptcy. Significant credit spreads widening caused by massive deleveraging. Shocks for DxS Factors are percentages of spread. | E83: - | G83: =+VLOOKUP(F83,[1]Explore!$B:$I,8,0) -> #N/A | H83: - | I83: =+VLOOKUP(H83,[1]Explore!$A:$I,9,0) -> #N/A | J83: =IF(AND(ISNA(G83),ISNA(I83)),"BOTH #N/A","OK") -> BOTH #N/A | K83: =IFERROR(I83, IFERROR(G83, L83)) -> - | L83: - | M83: =_xlfn.IFNA(VLOOKUP(K83,'Mapping DEF'!A:C,2,0),"") | N83: =+_xlfn.IFNA(VLOOKUP(M83,'Mapping DEF'!B:C,2,FALSE),"")
A84: CB_OVER | B84: Fed Policy at Growth Inflection-Economy Overheats(08/2021) | C84: 2461 | D84: The US economy recovers sharply following a successful vaccine rollout, leading to elevated risk asset valuations and unexpectedly high inflation. Faced with apparent economic overheating, the Fed hastens its tapering of asset purchases and pulls rate hike expectations forward to early 2022. | E84: Tsy 2Y USD_2yr - Yield: 20.00bps, | F84: Tsy 2Y | G84: =+VLOOKUP(F84,[1]Explore!$B:$I,8,0) -> Govt USD | H84: USD_2yr | I84: =+VLOOKUP(H84,[1]Explore!$A:$I,9,0) -> Govt USD | J84: =IF(AND(ISNA(G84),ISNA(I84)),"BOTH #N/A","OK") -> OK | K84: =IFERROR(I84, IFERROR(G84, L84)) -> Govt USD | L84: Yield | M84: =_xlfn.IFNA(VLOOKUP(K84,'Mapping DEF'!A:C,2,0),"") -> Curve (Local) | N84: =+_xlfn.IFNA(VLOOKUP(M84,'Mapping DEF'!B:C,2,FALSE),"") -> Term Structure | O84: 20.00bps
A85: CB_OVER | B85: Fed Policy at Growth Inflection-Economy Overheats(08/2021) | C85: 2461 | D85: The US economy recovers sharply following a successful vaccine rollout, leading to elevated risk asset valuations and unexpectedly high inflation. Faced with apparent economic overheating, the Fed hastens its tapering of asset purchases and pulls rate hike expectations forward to early 2022. | E85: Tsy 10Y USD_10yr - Yield: 45.00bps, | F85: Tsy 10Y | G85: =+VLOOKUP(F85,[1]Explore!$B:$I,8,0) -> Govt USD | H85: USD_10yr | I85: =+VLOOKUP(H85,[1]Explore!$A:$I,9,0) -> Govt USD | J85: =IF(AND(ISNA(G85),ISNA(I85)),"BOTH #N/A","OK") -> OK | K85: =IFERROR(I85, IFERROR(G85, L85)) -> Govt USD | L85: Yield | M85: =_xlfn.IFNA(VLOOKUP(K85,'Mapping DEF'!A:C,2,0),"") -> Curve (Local) | N85: =+_xlfn.IFNA(VLOOKUP(M85,'Mapping DEF'!B:C,2,FALSE),"") -> Term Structure | O85: 45.00bps
A86: CB_OVER | B86: Fed Policy at Growth Inflection-Economy Overheats(08/2021) | C86: 2461 | D86: The US economy recovers sharply following a successful vaccine rollout, leading to elevated risk asset valuations and unexpectedly high inflation. Faced with apparent economic overheating, the Fed hastens its tapering of asset purchases and pulls rate hike expectations forward to early 2022. | E86: USD INF 10Y USD_INF_10yr - Yield: -50.00bps, | F86: USD INF 10Y | G86: =+VLOOKUP(F86,[1]Explore!$B:$I,8,0) -> USD Inflation | H86: USD_INF_10yr | I86: =+VLOOKUP(H86,[1]Explore!$A:$I,9,0) -> USD Inflation | J86: =IF(AND(ISNA(G86),ISNA(I86)),"BOTH #N/A","OK") -> OK | K86: =IFERROR(I86, IFERROR(G86, L86)) -> USD Inflation | L86: Yield | M86: =_xlfn.IFNA(VLOOKUP(K86,'Mapping DEF'!A:C,2,0),"") -> Inflation | N86: =+_xlfn.IFNA(VLOOKUP(M86,'Mapping DEF'!B:C,2,FALSE),"") -> Other | O86: -50.00bps
A87: CB_OVER | B87: Fed Policy at Growth Inflection-Economy Overheats(08/2021) | C87: 2461 | D87: The US economy recovers sharply following a successful vaccine rollout, leading to elevated risk asset valuations and unexpectedly high inflation. Faced with apparent economic overheating, the Fed hastens its tapering of asset purchases and pulls rate hike expectations forward to early 2022. | E87: 15yr Mtg Tsy Basis USD_mtg15_tsy - Mortgage Basis: 20.00bps, | F87: 15yr Mtg Tsy Basis | G87: =+VLOOKUP(F87,[1]Explore!$B:$I,8,0) -> Mortgage Basis | H87: USD_mtg15_tsy | I87: =+VLOOKUP(H87,[1]Explore!$A:$I,9,0) -> Mortgage Basis | J87: =IF(AND(ISNA(G87),ISNA(I87)),"BOTH #N/A","OK") -> OK | K87: =IFERROR(I87, IFERROR(G87, L87)) -> Mortgage Basis | L87: Mortgage Basis | M87: =_xlfn.IFNA(VLOOKUP(K87,'Mapping DEF'!A:C,2,0),"") -> Alternative | N87: =+_xlfn.IFNA(VLOOKUP(M87,'Mapping DEF'!B:C,2,FALSE),"") -> Other | O87: 20.00bps
A88: CB_OVER | B88: Fed Policy at Growth Inflection-Economy Overheats(08/2021) | C88: 2461 | D88: The US economy recovers sharply following a successful vaccine rollout, leading to elevated risk asset valuations and unexpectedly high inflation. Faced with apparent economic overheating, the Fed hastens its tapering of asset purchases and pulls rate hike expectations forward to early 2022. | E88: Brent Crude ICE 1 USD_COMD_CO_1 - Price Level: 7.00pct, | F88: Brent Crude ICE 1 | G88: =+VLOOKUP(F88,[1]Explore!$B:$I,8,0) -> Alternative - Commodity | H88: USD_COMD_CO_1 | I88: =+VLOOKUP(H88,[1]Explore!$A:$I,9,0) -> Alternative - Commodity | J88: =IF(AND(ISNA(G88),ISNA(I88)),"BOTH #N/A","OK") -> OK | K88: =IFERROR(I88, IFERROR(G88, L88)) -> Alternative - Commodity | L88: Price Level | M88: =_xlfn.IFNA(VLOOKUP(K88,'Mapping DEF'!A:C,2,0),"") -> Alternative | N88: =+_xlfn.IFNA(VLOOKUP(M88,'Mapping DEF'!B:C,2,FALSE),"") -> Other | O88: 7.00pct
A89: CB_OVER | B89: Fed Policy at Growth Inflection-Economy Overheats(08/2021) | C89: 2461 | D89: The US economy recovers sharply following a successful vaccine rollout, leading to elevated risk asset valuations and unexpectedly high inflation. Faced with apparent economic overheating, the Fed hastens its tapering of asset purchases and pulls rate hike expectations forward to early 2022. | E89: Gold COMEX 1 USD_COMD_GC_1 - Price Level: 5.00pct, | F89: Gold COMEX 1 | G89: =+VLOOKUP(F89,[1]Explore!$B:$I,8,0) -> Alternative - Commodity | H89: USD_COMD_GC_1 | I89: =+VLOOKUP(H89,[1]Explore!$A:$I,9,0) -> Alternative - Commodity | J89: =IF(AND(ISNA(G89),ISNA(I89)),"BOTH #N/A","OK") -> OK | K89: =IFERROR(I89, IFERROR(G89, L89)) -> Alternative - Commodity | L89: Price Level | M89: =_xlfn.IFNA(VLOOKUP(K89,'Mapping DEF'!A:C,2,0),"") -> Alternative | N89: =+_xlfn.IFNA(VLOOKUP(M89,'Mapping DEF'!B:C,2,FALSE),"") -> Other | O89: 5.00pct
A90: CB_OVER | B90: Fed Policy at Growth Inflection-Economy Overheats(08/2021) | C90: 2461 | D90: The US economy recovers sharply following a successful vaccine rollout, leading to elevated risk asset valuations and unexpectedly high inflation. Faced with apparent economic overheating, the Fed hastens its tapering of asset purchases and pulls rate hike expectations forward to early 2022. | E90: US Cash Bonds IG USD_LEH_CREDIT3 - Spread Yield: 20.00bps, | F90: US Cash Bonds IG | G90: =+VLOOKUP(F90,[1]Explore!$B:$I,8,0) -> Corporate IG USD - Other | H90: USD_LEH_CREDIT3 | I90: =+VLOOKUP(H90,[1]Explore!$A:$I,9,0) -> Corporate IG USD - Other | J90: =IF(AND(ISNA(G90),ISNA(I90)),"BOTH #N/A","OK") -> OK | K90: =IFERROR(I90, IFERROR(G90, L90)) -> Corporate IG USD - Other | L90: Corporate IG USD - Other | M90: =_xlfn.IFNA(VLOOKUP(K90,'Mapping DEF'!A:C,2,0),"") -> Spread | N90: =+_xlfn.IFNA(VLOOKUP(M90,'Mapping DEF'!B:C,2,FALSE),"") -> Spread | O90: 20.00bps
A91: CB_OVER | B91: Fed Policy at Growth Inflection-Economy Overheats(08/2021) | C91: 2461 | D91: The US economy recovers sharply following a successful vaccine rollout, leading to elevated risk asset valuations and unexpectedly high inflation. Faced with apparent economic overheating, the Fed hastens its tapering of asset purchases and pulls rate hike expectations forward to early 2022. | E91: DXY DXY - Index Level: 3.00pct, | F91: DXY | G91: =+VLOOKUP(F91,[1]Explore!$B:$I,8,0) -> #N/A | H91: DXY | I91: =+VLOOKUP(H91,[1]Explore!$A:$I,9,0) -> #N/A | J91: =IF(AND(ISNA(G91),ISNA(I91)),"BOTH #N/A","OK") -> BOTH #N/A | K91: =IFERROR(I91, IFERROR(G91, L91)) -> Dollar Index | L91: Dollar Index | M91: =_xlfn.IFNA(VLOOKUP(K91,'Mapping DEF'!A:C,2,0),"") -> Index Level | N91: =+_xlfn.IFNA(VLOOKUP(M91,'Mapping DEF'!B:C,2,FALSE),"") -> Other | O91: 3.00pct
A92: CB_OVER | B92: Fed Policy at Growth Inflection-Economy Overheats(08/2021) | C92: 2461 | D92: The US economy recovers sharply following a successful vaccine rollout, leading to elevated risk asset valuations and unexpectedly high inflation. Faced with apparent economic overheating, the Fed hastens its tapering of asset purchases and pulls rate hike expectations forward to early 2022. | E92: S&P 500 SPX - Index Level: -8.00pct, | F92: S&P 500 | G92: =+VLOOKUP(F92,[1]Explore!$B:$I,8,0) -> Equity Implied Volatility | H92: SPX | I92: =+VLOOKUP(H92,[1]Explore!$A:$I,9,0) -> Equity Implied Volatility | J92: =IF(AND(ISNA(G92),ISNA(I92)),"BOTH #N/A","OK") -> OK | K92: =IFERROR(I92, IFERROR(G92, L92)) -> Equity Implied Volatility | L92: Index Level | M92: =_xlfn.IFNA(VLOOKUP(K92,'Mapping DEF'!A:C,2,0),"") -> Equity Derivatives | N92: =+_xlfn.IFNA(VLOOKUP(M92,'Mapping DEF'!B:C,2,FALSE),"") -> Equity | O92: -8.00pct
A93: CB_OVER | B93: Fed Policy at Growth Inflection-Economy Overheats(08/2021) | C93: 2461 | D93: The US economy recovers sharply following a successful vaccine rollout, leading to elevated risk asset valuations and unexpectedly high inflation. Faced with apparent economic overheating, the Fed hastens its tapering of asset purchases and pulls rate hike expectations forward to early 2022. | E93: Time ALL_TIME - Time: 30.00days, | F93: Time | G93: =+VLOOKUP(F93,[1]Explore!$B:$I,8,0) -> #N/A | H93: ALL_TIME | I93: =+VLOOKUP(H93,[1]Explore!$A:$I,9,0) -> #N/A | J93: =IF(AND(ISNA(G93),ISNA(I93)),"BOTH #N/A","OK") -> BOTH #N/A | K93: =IFERROR(I93, IFERROR(G93, L93)) -> Time | L93: Time | M93: =_xlfn.IFNA(VLOOKUP(K93,'Mapping DEF'!A:C,2,0),"") -> Time | N93: =+_xlfn.IFNA(VLOOKUP(M93,'Mapping DEF'!B:C,2,FALSE),"") -> Other | O93: 30.00days
A94: CB_OVER | B94: Fed Policy at Growth Inflection-Economy Overheats(08/2021) | C94: 2461 | D94: The US economy recovers sharply following a successful vaccine rollout, leading to elevated risk asset valuations and unexpectedly high inflation. Faced with apparent economic overheating, the Fed hastens its tapering of asset purchases and pulls rate hike expectations forward to early 2022. | E94: US HY Market USD_HY_MARKET - Spread Yield: 50.00bps, | F94: US HY Market | G94: =+VLOOKUP(F94,[1]Explore!$B:$I,8,0) -> Corporate HY USD - Other | H94: USD_HY_MARKET | I94: =+VLOOKUP(H94,[1]Explore!$A:$I,9,0) -> Corporate HY USD - Other | J94: =IF(AND(ISNA(G94),ISNA(I94)),"BOTH #N/A","OK") -> OK | K94: =IFERROR(I94, IFERROR(G94, L94)) -> Corporate HY USD - Other | L94: Spread Yield | M94: =_xlfn.IFNA(VLOOKUP(K94,'Mapping DEF'!A:C,2,0),"") -> Spread | N94: =+_xlfn.IFNA(VLOOKUP(M94,'Mapping DEF'!B:C,2,FALSE),"") -> Spread | O94: 50.00bps
A95: CB_OVER | B95: Fed Policy at Growth Inflection-Economy Overheats(08/2021) | C95: 2461 | D95: The US economy recovers sharply following a successful vaccine rollout, leading to elevated risk asset valuations and unexpectedly high inflation. Faced with apparent economic overheating, the Fed hastens its tapering of asset purchases and pulls rate hike expectations forward to early 2022. | E95: S&P 500 Consumer Staples Index - S&P 500 [SPCS-SPX] - Index Level: 10.00pct | F95: S&P 500 Consumer Staples Index | G95: =+VLOOKUP(F95,[1]Explore!$B:$I,8,0) -> Other - Index | H95: Index | I95: =+VLOOKUP(H95,[1]Explore!$A:$I,9,0) -> #N/A | J95: =IF(AND(ISNA(G95),ISNA(I95)),"BOTH #N/A","OK") -> OK | K95: =IFERROR(I95, IFERROR(G95, L95)) -> Other - Index | L95: Index Level | M95: =_xlfn.IFNA(VLOOKUP(K95,'Mapping DEF'!A:C,2,0),"") -> Other | N95: =+_xlfn.IFNA(VLOOKUP(M95,'Mapping DEF'!B:C,2,FALSE),"") -> Other | O95: 10.00pct
... A146: CEM_LATAM | B146: EM Pandemic Crisis - Widespread Infections Devastate LatAm | C146: 2445 | D146: A jump in infection rates results in strict lockdowns across most of LatAm. Regional central banks loosen monetary policy in an effort to stimulate their economies, but markets panic as political instability rises and lockdown measures persist. | E146: EMBIG DxS USD_EM_DS_G - Spread Yield 100.00 bps, | F146: EMBIG DxS | G146: =+VLOOKUP(F146,[1]Explore!$B:$I,8,0) -> Spread Emerging Markets - Country | H146: USD_EM_DS_G | I146: =+VLOOKUP(H146,[1]Explore!$A:$I,9,0) -> Spread Emerging Markets - Country | J146: =IF(AND(ISNA(G146),ISNA(I146)),"BOTH #N/A","OK") -> OK | K146: =IFERROR(I146, IFERROR(G146, L146)) -> Spread Emerging Markets - Country | L146: Spread Yield | M146: =_xlfn.IFNA(VLOOKUP(K146,'Mapping DEF'!A:C,2,0),"") -> Spread | N146: =+_xlfn.IFNA(VLOOKUP(M146,'Mapping DEF'!B:C,2,FALSE),"") -> Spread | O146: 100.00bps
A147: CEM_LATAM | B147: EM Pandemic Crisis - Widespread Infections Devastate LatAm | C147: 2445 | D147: A jump in infection rates results in strict lockdowns across most of LatAm. Regional central banks loosen monetary policy in an effort to stimulate their economies, but markets panic as political instability rises and lockdown measures persist. | E147: Middle East and Africa USD_EM_CORP_MIDAF - Spread Yield 200.00 bps | F147: Middle East and Africa | G147: Spread Yield | H147: USD_EM_CORP_MIDAF | I147: =+VLOOKUP(H147,[1]Explore!$A:$I,9,0) -> Other - Spread Yield | J147: =IF(AND(ISNA(G147),ISNA(I147)),"BOTH #N/A","OK") -> OK | K147: =IFERROR(I147, IFERROR(G147, L147)) -> Other - Spread Yield | L147: Spread Yield | M147: =_xlfn.IFNA(VLOOKUP(K147,'Mapping DEF'!A:C,2,0),"") | N147: =+_xlfn.IFNA(VLOOKUP(M147,'Mapping DEF'!B:C,2,FALSE),"") | O147: 200.00bps
A148: CEM_LATAM | B148: EM Pandemic Crisis - Widespread Infections Devastate LatAm | C148: 2445 | D148: A jump in infection rates results in strict lockdowns across most of LatAm. Regional central banks loosen monetary policy in an effort to stimulate their economies, but markets panic as political instability rises and lockdown measures persist. | E148: BRL 3M BRL_3m - Yield -100.00 bps, | F148: BRL 3M | G148: =+VLOOKUP(F148,[1]Explore!$B:$I,8,0) -> Govt Emerging Markets | H148: BRL_3m | I148: =+VLOOKUP(H148,[1]Explore!$A:$I,9,0) -> Govt Emerging Markets | J148: =IF(AND(ISNA(G148),ISNA(I148)),"BOTH #N/A","OK") -> OK | K148: =IFERROR(I148, IFERROR(G148, L148)) -> Govt Emerging Markets | L148: Yield | M148: =_xlfn.IFNA(VLOOKUP(K148,'Mapping DEF'!A:C,2,0),"") -> Curve (Local) | N148: =+_xlfn.IFNA(VLOOKUP(M148,'Mapping DEF'!B:C,2,FALSE),"") -> Term Structure | O148: -100.00bps
A149: CEM_LATAM | B149: EM Pandemic Crisis - Widespread Infections Devastate LatAm | C149: 2445 | D149: A jump in infection rates results in strict lockdowns across most of LatAm. Regional central banks loosen monetary policy in an effort to stimulate their economies, but markets panic as political instability rises and lockdown measures persist. | E149: BRL 10Y BRL_10yr - Yield 100.00 bps, | F149: BRL 10Y | G149: =+VLOOKUP(F149,[1]Explore!$B:$I,8,0) -> Govt Emerging Markets | H149: BRL_10yr | I149: =+VLOOKUP(H149,[1]Explore!$A:$I,9,0) -> Govt Emerging Markets | J149: =IF(AND(ISNA(G149),ISNA(I149)),"BOTH #N/A","OK") -> OK | K149: =IFERROR(I149, IFERROR(G149, L149)) -> Govt Emerging Markets | L149: Yield | M149: =_xlfn.IFNA(VLOOKUP(K149,'Mapping DEF'!A:C,2,0),"") -> Curve (Local) | N149: =+_xlfn.IFNA(VLOOKUP(M149,'Mapping DEF'!B:C,2,FALSE),"") -> Term Structure | O149: 100.00bps
A150: CEM_LATAM | B150: EM Pandemic Crisis - Widespread Infections Devastate LatAm | C150: 2445 | D150: A jump in infection rates results in strict lockdowns across most of LatAm. Regional central banks loosen monetary policy in an effort to stimulate their economies, but markets panic as political instability rises and lockdown measures persist. | E150: BRL/USD BRL_FX_USD - FX -20.00 pct, | F150: BRLUSD | G150: =+VLOOKUP(F150,[1]Explore!$B:$I,8,0) -> #N/A | H150: BRL_FX_USD | I150: =+VLOOKUP(H150,[1]Explore!$A:$I,9,0) -> Emerging Currency | J150: =IF(AND(ISNA(G150),ISNA(I150)),"BOTH #N/A","OK") -> OK | K150: =IFERROR(I150, IFERROR(G150, L150)) -> Emerging Currency | L150: FX | M150: =_xlfn.IFNA(VLOOKUP(K150,'Mapping DEF'!A:C,2,0),"") -> FX | N150: =+_xlfn.IFNA(VLOOKUP(M150,'Mapping DEF'!B:C,2,FALSE),"") -> FX | O150: -20.00pct
A151: CEM_LATAM | B151: EM Pandemic Crisis - Widespread Infections Devastate LatAm | C151: 2445 | D151: A jump in infection rates results in strict lockdowns across most of LatAm. Regional central banks loosen monetary policy in an effort to stimulate their economies, but markets panic as political instability rises and lockdown measures persist. | E151: VIX VIX - Index Level 30.00 pct, | F151: VIX | G151: =+VLOOKUP(F151,[1]Explore!$B:$I,8,0) -> Equity Implied Volatility | H151: VIX | I151: =+VLOOKUP(H151,[1]Explore!$A:$I,9,0) -> Equity Implied Volatility | J151: =IF(AND(ISNA(G151),ISNA(I151)),"BOTH #N/A","OK") -> OK | K151: =IFERROR(I151, IFERROR(G151, L151)) -> Equity Implied Volatility | L151: Index Level | M151: =_xlfn.IFNA(VLOOKUP(K151,'Mapping DEF'!A:C,2,0),"") -> Equity Derivatives | N151: =+_xlfn.IFNA(VLOOKUP(M151,'Mapping DEF'!B:C,2,FALSE),"") -> Equity | O151: 30.00pct
A152: CEM_LATAM | B152: EM Pandemic Crisis - Widespread Infections Devastate LatAm | C152: 2445 | D152: A jump in infection rates results in strict lockdowns across most of LatAm. Regional central banks loosen monetary policy in an effort to stimulate their economies, but markets panic as political instability rises and lockdown measures persist. | E152: Time ALL_TIME - Time 30.00 days, | F152: Time | G152: =+VLOOKUP(F152,[1]Explore!$B:$I,8,0) -> #N/A | H152: ALL_TIME | I152: =+VLOOKUP(H152,[1]Explore!$A:$I,9,0) -> #N/A | J152: =IF(AND(ISNA(G152),ISNA(I152)),"BOTH #N/A","OK") -> BOTH #N/A | K152: =IFERROR(I152, IFERROR(G152, L152)) -> Time | L152: Time | M152: =_xlfn.IFNA(VLOOKUP(K152,'Mapping DEF'!A:C,2,0),"") -> Time | N152: =+_xlfn.IFNA(VLOOKUP(M152,'Mapping DEF'!B:C,2,FALSE),"") -> Other | O152: 30.00days
A153: CEM_LATAM | B153: EM Pandemic Crisis - Widespread Infections Devastate LatAm | C153: 2445 | D153: A jump in infection rates results in strict lockdowns across most of LatAm. Regional central banks loosen monetary policy in an effort to stimulate their economies, but markets panic as political instability rises and lockdown measures persist. | E153: Cons Staples x Alcohol & Tob FMI_LATC_CSTXALCTOB - Industry Return 10.00 pct, | F153: Cons Staples x Alcohol & Tob | G153: =+VLOOKUP(F153,[1]Explore!$B:$I,8,0) -> Consumer Staples | H153: FMI_LATC_CSTXALCTOB | I153: =+VLOOKUP(H153,[1]Explore!$A:$I,9,0) -> #N/A | J153: =IF(AND(ISNA(G153),ISNA(I153)),"BOTH #N/A","OK") -> OK | K153: =IFERROR(I153, IFERROR(G153, L153)) -> Consumer Staples | L153: Industry Return | M153: =_xlfn.IFNA(VLOOKUP(K153,'Mapping DEF'!A:C,2,0),"") -> Industry Allocation | N153: =+_xlfn.IFNA(VLOOKUP(M153,'Mapping DEF'!B:C,2,FALSE),"") -> Equity | O153: 10.00pct
A154: CEM_LATAM | B154: EM Pandemic Crisis - Widespread Infections Devastate LatAm | C154: 2445 | D154: A jump in infection rates results in strict lockdowns across most of LatAm. Regional central banks loosen monetary policy in an effort to stimulate their economies, but markets panic as political instability rises and lockdown measures persist. | E154: Banks FMI_LATC_FINBANK - Industry Return -10.00 pct, | F154: Banks | G154: =+VLOOKUP(F154,[1]Explore!$B:$I,8,0) -> #N/A | H154: FMI_LATC_FINBANK | I154: =+VLOOKUP(H154,[1]Explore!$A:$I,9,0) -> #N/A | J154: =IF(AND(ISNA(G154),ISNA(I154)),"BOTH #N/A","OK") -> BOTH #N/A | K154: =IFERROR(I154, IFERROR(G154, L154)) -> Financials | L154: Financials | M154: =_xlfn.IFNA(VLOOKUP(K154,'Mapping DEF'!A:C,2,0),"") -> Industry Allocation | N154: =+_xlfn.IFNA(VLOOKUP(M154,'Mapping DEF'!B:C,2,FALSE),"") -> Equity | O154: -10.00pct
A155: CEM_LATAM | B155: EM Pandemic Crisis - Widespread Infections Devastate LatAm | C155: 2445 | D155: A jump in infection rates results in strict lockdowns across most of LatAm. Regional central banks loosen monetary policy in an effort to stimulate their economies, but markets panic as political instability rises and lockdown measures persist. | E155: EMBIG DxS USD_EM_DS_G - Spread Yield 100.00 bps, | F155: EMBIG DxS | G155: =+VLOOKUP(F155,[1]Explore!$B:$I,8,0) -> Spread Emerging Markets - Country | H155: USD_EM_DS_G | I155: =+VLOOKUP(H155,[1]Explore!$A:$I,9,0) -> Spread Emerging Markets - Country | J155: =IF(AND(ISNA(G155),ISNA(I155)),"BOTH #N/A","OK") -> OK | K155: =IFERROR(I155, IFERROR(G155, L155)) -> Spread Emerging Markets - Country | L155: Spread Yield | M155: =_xlfn.IFNA(VLOOKUP(K155,'Mapping DEF'!A:C,2,0),"") -> Spread | N155: =+_xlfn.IFNA(VLOOKUP(M155,'Mapping DEF'!B:C,2,FALSE),"") -> Spread | O155: 100.00bps
A156: CEM_LATAM | B156: EM Pandemic Crisis - Widespread Infections Devastate LatAm | C156: 2445 | D156: A jump in infection rates results in strict lockdowns across most of LatAm. Regional central banks loosen monetary policy in an effort to stimulate their economies, but markets panic as political instability rises and lockdown measures persist. | E156: Mexico USD_EM_DS_MEXICO - Spread Yield 200.00 bps, | F156: Mexico | G156: =+VLOOKUP(F156,[1]Explore!$B:$I,8,0) -> Emerging Markets | H156: USD_EM_DS_MEXICO | I156: =+VLOOKUP(H156,[1]Explore!$A:$I,9,0) -> Spread Emerging Markets - Country | J156: =IF(AND(ISNA(G156),ISNA(I156)),"BOTH #N/A","OK") -> OK | K156: =IFERROR(I156, IFERROR(G156, L156)) -> Spread Emerging Markets - Country | L156: Spread Yield | M156: =_xlfn.IFNA(VLOOKUP(K156,'Mapping DEF'!A:C,2,0),"") -> Spread | N156: =+_xlfn.IFNA(VLOOKUP(M156,'Mapping DEF'!B:C,2,FALSE),"") -> Spread | O156: 200.00bps
A157: CEM_LATAM | B157: EM Pandemic Crisis - Widespread Infections Devastate LatAm | C157: 2445 | D157: A jump in infection rates results in strict lockdowns across most of LatAm. Regional central banks loosen monetary policy in an effort to stimulate their economies, but markets panic as political instability rises and lockdown measures persist. | E157: MSCI EM Latin America (Loc) MS_LA_LCL - Index Level -20.00 pct, | F157: MSCI EM Latin America Loc | G157: =+VLOOKUP(F157,[1]Explore!$B:$I,8,0) -> #N/A | H157: MS_LA_LCL | I157: =+VLOOKUP(H157,[1]Explore!$A:$I,9,0) -> Other - Index | J157: =IF(AND(ISNA(G157),ISNA(I157)),"BOTH #N/A","OK") -> OK | K157: =IFERROR(I157, IFERROR(G157, L157)) -> Other - Index | L157: Index Level | M157: =_xlfn.IFNA(VLOOKUP(K157,'Mapping DEF'!A:C,2,0),"") -> Other | N157: =+_xlfn.IFNA(VLOOKUP(M157,'Mapping DEF'!B:C,2,FALSE),"") -> Other | O157: -20.00pct
A158: CEM_LATAM | B158: EM Pandemic Crisis - Widespread Infections Devastate LatAm | C158: 2445 | D158: A jump in infection rates results in strict lockdowns across most of LatAm. Regional central banks loosen monetary policy in an effort to stimulate their economies, but markets panic as political instability rises and lockdown measures persist. | E158: LA Industrial USD_EM_CORP_SA_INDU - Spread Yield 200.00 bps | F158: LA Industrial | G158: =+VLOOKUP(F158,[1]Explore!$B:$I,8,0) -> Corporate HY USD - Industry | H158: USD_EM_CORP_SA_INDU | I158: =+VLOOKUP(H158,[1]Explore!$A:$I,9,0) -> Corporate HY USD - Industry | J158: =IF(AND(ISNA(G158),ISNA(I158)),"BOTH #N/A","OK") -> OK | K158: =IFERROR(I158, IFERROR(G158, L158)) -> Corporate HY USD - Industry | L158: Spread Yield | M158: =_xlfn.IFNA(VLOOKUP(K158,'Mapping DEF'!A:C,2,0),"") -> Spread | N158: =+_xlfn.IFNA(VLOOKUP(M158,'Mapping DEF'!B:C,2,FALSE),"") -> Spread | O158: 200.00bps
A159: CHINA15A | B159: Chinese Market Crash '15 - Absolute, June 12 - Aug 26, 2015 | C159: 2318 | D159: A jump in infection rates results in strict lockdowns across most of LatAm. Regional central banks loosen monetary policy in an effort to stimulate their economies, but markets panic as political instability rises and lockdown measures persist. | E159: - | G159: =+VLOOKUP(F159,[1]Explore!$B:$I,8,0) -> #N/A | H159: - | I159: =+VLOOKUP(H159,[1]Explore!$A:$I,9,0) -> #N/A | J159: =IF(AND(ISNA(G159),ISNA(I159)),"BOTH #N/A","OK") -> BOTH #N/A | K159: =IFERROR(I159, IFERROR(G159, L159)) -> - | L159: - | M159: =_xlfn.IFNA(VLOOKUP(K159,'Mapping DEF'!A:C,2,0),"") | N159: =+_xlfn.IFNA(VLOOKUP(M159,'Mapping DEF'!B:C,2,FALSE),"")
A160: CHINA15R | B160: Chinese Market Crash '15 - Relative, June 12 - Aug 26, 2015 | C160: 2317 | D160: A jump in infection rates results in strict lockdowns across most of LatAm. Regional central banks loosen monetary policy in an effort to stimulate their economies, but markets panic as political instability rises and lockdown measures persist. | E160: - | G160: =+VLOOKUP(F160,[1]Explore!$B:$I,8,0) -> #N/A | H160: - | I160: =+VLOOKUP(H160,[1]Explore!$A:$I,9,0) -> #N/A | J160: =IF(AND(ISNA(G160),ISNA(I160)),"BOTH #N/A","OK") -> BOTH #N/A | K160: =IFERROR(I160, IFERROR(G160, L160)) -> - | L160: - | M160: =_xlfn.IFNA(VLOOKUP(K160,'Mapping DEF'!A:C,2,0),"") | N160: =+_xlfn.IFNA(VLOOKUP(M160,'Mapping DEF'!B:C,2,FALSE),"")
A161: CHNTD_GLB | B161: US-China Trade Relations - Global Trade Protectionism | C161: 2412 | D161: A jump in infection rates results in strict lockdowns across most of LatAm. Regional central banks loosen monetary policy in an effort to stimulate their economies, but markets panic as political instability rises and lockdown measures persist. | E161: Tsy 10Y USD_10yr - Yield -35.00 bps, | F161: Tsy 10Y | G161: =+VLOOKUP(F161,[1]Explore!$B:$I,8,0) -> Govt USD | H161: USD_10yr | I161: =+VLOOKUP(H161,[1]Explore!$A:$I,9,0) -> Govt USD | J161: =IF(AND(ISNA(G161),ISNA(I161)),"BOTH #N/A","OK") -> OK | K161: =IFERROR(I161, IFERROR(G161, L161)) -> Govt USD | L161: Yield | M161: =_xlfn.IFNA(VLOOKUP(K161,'Mapping DEF'!A:C,2,0),"") -> Curve (Local) | N161: =+_xlfn.IFNA(VLOOKUP(M161,'Mapping DEF'!B:C,2,FALSE),"") -> Term Structure | O161: -35.00bps
A162: CHNTD_GLB | B162: US-China Trade Relations - Global Trade Protectionism | C162: 2412 | D162: A jump in infection rates results in strict lockdowns across most of LatAm. Regional central banks loosen monetary policy in an effort to stimulate their economies, but markets panic as political instability rises and lockdown measures persist. | E162: USD INF 10Y USD_INF_10yr - Yield -20.00 bps, | F162: USD INF 10Y | G162: =+VLOOKUP(F162,[1]Explore!$B:$I,8,0) -> USD Inflation | H162: USD_INF_10yr | I162: =+VLOOKUP(H162,[1]Explore!$A:$I,9,0) -> USD Inflation | J162: =IF(AND(ISNA(G162),ISNA(I162)),"BOTH #N/A","OK") -> OK | K162: =IFERROR(I162, IFERROR(G162, L162)) -> USD Inflation | L162: Yield | M162: =_xlfn.IFNA(VLOOKUP(K162,'Mapping DEF'!A:C,2,0),"") -> Inflation | N162: =+_xlfn.IFNA(VLOOKUP(M162,'Mapping DEF'!B:C,2,FALSE),"") -> Other | O162: -20.00bps
A163: CHNTD_GLB | B163: US-China Trade Relations - Global Trade Protectionism | C163: 2412 | D163: A jump in infection rates results in strict lockdowns across most of LatAm. Regional central banks loosen monetary policy in an effort to stimulate their economies, but markets panic as political instability rises and lockdown measures persist. | E163: Copper CMX 1 USD_COMD_HG_1 - Price Level -10.00 pct, | F163: Copper CMX 1 | G163: =+VLOOKUP(F163,[1]Explore!$B:$I,8,0) -> Alternative - Commodity | H163: USD_COMD_HG_1 | I163: =+VLOOKUP(H163,[1]Explore!$A:$I,9,0) -> Alternative - Commodity | J163: =IF(AND(ISNA(G163),ISNA(I163)),"BOTH #N/A","OK") -> OK | K163: =IFERROR(I163, IFERROR(G163, L163)) -> Alternative - Commodity | L163: Price Level | M163: =_xlfn.IFNA(VLOOKUP(K163,'Mapping DEF'!A:C,2,0),"") -> Alternative | N163: =+_xlfn.IFNA(VLOOKUP(M163,'Mapping DEF'!B:C,2,FALSE),"") -> Other | O163: -10.00pct
A164: CHNTD_GLB | B164: US-China Trade Relations - Global Trade Protectionism | C164: 2412 | D164: A jump in infection rates results in strict lockdowns across most of LatAm. Regional central banks loosen monetary policy in an effort to stimulate their economies, but markets panic as political instability rises and lockdown measures persist. | E164: Gold COMEX 1 USD_COMD_GC_1 - Price Level 6.00 pct, | F164: Gold COMEX 1 | G164: =+VLOOKUP(F164,[1]Explore!$B:$I,8,0) -> Alternative - Commodity | H164: USD_COMD_GC_1 | I164: =+VLOOKUP(H164,[1]Explore!$A:$I,9,0) -> Alternative - Commodity | J164: =IF(AND(ISNA(G164),ISNA(I164)),"BOTH #N/A","OK") -> OK | K164: =IFERROR(I164, IFERROR(G164, L164)) -> Alternative - Commodity | L164: Price Level | M164: =_xlfn.IFNA(VLOOKUP(K164,'Mapping DEF'!A:C,2,0),"") -> Alternative | N164: =+_xlfn.IFNA(VLOOKUP(M164,'Mapping DEF'!B:C,2,FALSE),"") -> Other | O164: 6.00pct
A165: CHNTD_GLB | B165: US-China Trade Relations - Global Trade Protectionism | C165: 2412 | D165: A jump in infection rates results in strict lockdowns across most of LatAm. Regional central banks loosen monetary policy in an effort to stimulate their economies, but markets panic as political instability rises and lockdown measures persist. | E165: MXN 10Y MXN_10yr - Yield 80.00 bps, | F165: MXN 10Y | G165: =+VLOOKUP(F165,[1]Explore!$B:$I,8,0) -> Govt Emerging Markets | H165: MXN_10yr | I165: =+VLOOKUP(H165,[1]Explore!$A:$I,9,0) -> Govt Emerging Markets | J165: =IF(AND(ISNA(G165),ISNA(I165)),"BOTH #N/A","OK") -> OK | K165: =IFERROR(I165, IFERROR(G165, L165)) -> Govt Emerging Markets | L165: Yield | M165: =_xlfn.IFNA(VLOOKUP(K165,'Mapping DEF'!A:C,2,0),"") -> Curve (Local) | N165: =+_xlfn.IFNA(VLOOKUP(M165,'Mapping DEF'!B:C,2,FALSE),"") -> Term Structure | O165: 80.00bps
A166: CHNTD_GLB | B166: US-China Trade Relations - Global Trade Protectionism | C166: 2412 | D166: A jump in infection rates results in strict lockdowns across most of LatAm. Regional central banks loosen monetary policy in an effort to stimulate their economies, but markets panic as political instability rises and lockdown measures persist. | E166: CNY/USD CNY_FX_USD - FX -2.00 pct, | F166: CNYUSD | G166: =+VLOOKUP(F166,[1]Explore!$B:$I,8,0) -> #N/A | H166: CNY_FX_USD | I166: =+VLOOKUP(H166,[1]Explore!$A:$I,9,0) -> Emerging Currency | J166: =IF(AND(ISNA(G166),ISNA(I166)),"BOTH #N/A","OK") -> OK | K166: =IFERROR(I166, IFERROR(G166, L166)) -> Emerging Currency | L166: FX | M166: =_xlfn.IFNA(VLOOKUP(K166,'Mapping DEF'!A:C,2,0),"") -> FX | N166: =+_xlfn.IFNA(VLOOKUP(M166,'Mapping DEF'!B:C,2,FALSE),"") -> FX | O166: -2.00pct
A167: CHNTD_GLB | B167: US-China Trade Relations - Global Trade Protectionism | C167: 2412 | D167: A jump in infection rates results in strict lockdowns across most of LatAm. Regional central banks loosen monetary policy in an effort to stimulate their economies, but markets panic as political instability rises and lockdown measures persist. | E167: MXN/USD MXN_FX_USD - FX -8.00 pct, | F167: MXNUSD | G167: =+VLOOKUP(F167,[1]Explore!$B:$I,8,0) -> #N/A | H167: MXN_FX_USD | I167: =+VLOOKUP(H167,[1]Explore!$A:$I,9,0) -> Emerging Currency | J167: =IF(AND(ISNA(G167),ISNA(I167)),"BOTH #N/A","OK") -> OK | K167: =IFERROR(I167, IFERROR(G167, L167)) -> Emerging Currency | L167: FX | M167: =_xlfn.IFNA(VLOOKUP(K167,'Mapping DEF'!A:C,2,0),"") -> FX | N167: =+_xlfn.IFNA(VLOOKUP(M167,'Mapping DEF'!B:C,2,FALSE),"") -> FX | O167: -8.00pct
A168: CHNTD_GLB | B168: US-China Trade Relations - Global Trade Protectionism | C168: 2412 | D168: Chinese stock market crash beginning with the popping of the stock market bubble on 12 June 2015 | E168: DXY DXY - Index Level 3.00 pct, | F168: DXY | G168: =+VLOOKUP(F168,[1]Explore!$B:$I,8,0) -> #N/A | H168: DXY | I168: =+VLOOKUP(H168,[1]Explore!$A:$I,9,0) -> #N/A | J168: =IF(AND(ISNA(G168),ISNA(I168)),"BOTH #N/A","OK") -> BOTH #N/A | K168: =IFERROR(I168, IFERROR(G168, L168)) -> Dollar Index | L168: Dollar Index | M168: =_xlfn.IFNA(VLOOKUP(K168,'Mapping DEF'!A:C,2,0),"") -> Index Level | N168: =+_xlfn.IFNA(VLOOKUP(M168,'Mapping DEF'!B:C,2,FALSE),"") -> Other | O168: 3.00pct
A169: CHNTD_GLB | B169: US-China Trade Relations - Global Trade Protectionism | C169: 2412 | D169: Chinese stock market crash beginning with the popping of the stock market bubble on 12 June 2015 | E169: S&P 500 SPX - Index Level -8.00 pct, | F169: S&P 500 | G169: =+VLOOKUP(F169,[1]Explore!$B:$I,8,0) -> Equity Implied Volatility | H169: SPX | I169: =+VLOOKUP(H169,[1]Explore!$A:$I,9,0) -> Equity Implied Volatility | J169: =IF(AND(ISNA(G169),ISNA(I169)),"BOTH #N/A","OK") -> OK | K169: =IFERROR(I169, IFERROR(G169, L169)) -> Equity Implied Volatility | L169: Index Level | M169: =_xlfn.IFNA(VLOOKUP(K169,'Mapping DEF'!A:C,2,0),"") -> Equity Derivatives | N169: =+_xlfn.IFNA(VLOOKUP(M169,'Mapping DEF'!B:C,2,FALSE),"") -> Equity | O169: -8.00pct
A170: CHNTD_GLB | B170: US-China Trade Relations - Global Trade Protectionism | C170: 2412 | D170: US-China Trade Relations - Global Trade Protectionism: US protectionism escalates trade disputes, and market sentiment deteriorates amid fears of a global trade war. | E170: Global HY 5 ALL_GLB_CORP_HY_5Y - Spread Yield 60.00 bps, | F170: Global HY 5 | G170: =+VLOOKUP(F170,[1]Explore!$B:$I,8,0) -> Corporate HY Other - Maturity | H170: ALL_GLB_CORP_HY_5Y | I170: =+VLOOKUP(H170,[1]Explore!$A:$I,9,0) -> Corporate HY Other - Maturity | J170: =IF(AND(ISNA(G170),ISNA(I170)),"BOTH #N/A","OK") -> OK | K170: =IFERROR(I170, IFERROR(G170, L170)) -> Corporate HY Other - Maturity | L170: Spread Yield | M170: =_xlfn.IFNA(VLOOKUP(K170,'Mapping DEF'!A:C,2,0),"") -> Spread | N170: =+_xlfn.IFNA(VLOOKUP(M170,'Mapping DEF'!B:C,2,FALSE),"") -> Spread | O170: 60.00bps
A171: CHNTD_GLB | B171: US-China Trade Relations - Global Trade Protectionism | C171: 2412 | D171: US-China Trade Relations - Global Trade Protectionism: US protectionism escalates trade disputes, and market sentiment deteriorates amid fears of a global trade war. | E171: EMBIG DxS USD_EM_DS_G - Spread Yield 80.00 bps, | F171: EMBIG DxS | G171: =+VLOOKUP(F171,[1]Explore!$B:$I,8,0) -> Spread Emerging Markets - Country | H171: USD_EM_DS_G | I171: =+VLOOKUP(H171,[1]Explore!$A:$I,9,0) -> Spread Emerging Markets - Country | J171: =IF(AND(ISNA(G171),ISNA(I171)),"BOTH #N/A","OK") -> OK | K171: =IFERROR(I171, IFERROR(G171, L171)) -> Spread Emerging Markets - Country | L171: Spread Yield | M171: =_xlfn.IFNA(VLOOKUP(K171,'Mapping DEF'!A:C,2,0),"") -> Spread | N171: =+_xlfn.IFNA(VLOOKUP(M171,'Mapping DEF'!B:C,2,FALSE),"") -> Spread | O171: 80.00bps
A172: CHNTD_GLB | B172: US-China Trade Relations - Global Trade Protectionism | C172: 2412 | D172: US-China Trade Relations - Global Trade Protectionism: US protectionism escalates trade disputes, and market sentiment deteriorates amid fears of a global trade war. | E172: China Corp HY USD_CN_CORP_HY - Spread Yield 150.00 bps, | F172: China Corp HY | G172: =+VLOOKUP(F172,[1]Explore!$B:$I,8,0) -> Corporate HY USD - Industry | H172: USD_CN_CORP_HY | I172: =+VLOOKUP(H172,[1]Explore!$A:$I,9,0) -> Corporate HY USD - Industry | J172: =IF(AND(ISNA(G172),ISNA(I172)),"BOTH #N/A","OK") -> OK | K172: =IFERROR(I172, IFERROR(G172, L172)) -> Corporate HY USD - Industry | L172: Spread Yield | M172: =_xlfn.IFNA(VLOOKUP(K172,'Mapping DEF'!A:C,2,0),"") -> Spread | N172: =+_xlfn.IFNA(VLOOKUP(M172,'Mapping DEF'!B:C,2,FALSE),"") -> Spread | O172: 150.00bps
... A316: COVID_V | B316: Pandemic Recession - Moderate Recovery | C316: 2442 | D316: Governments relax lockdown measures after successfully containing the COVID-19 outbreak. A moderate recovery in global growth follows a sharp contraction and significant policy easing. | E316: US Cash Bonds IG - EU Credit IG [USD_LEH_CREDIT3-EUR_LEH_CREDIT] - Spread Yield -30.00 bps | F316: US Cash Bonds IG | G316: =+VLOOKUP(F316,[1]Explore!$B:$I,8,0) -> Corporate IG USD - Other | H316: IG | I316: =+VLOOKUP(H316,[1]Explore!$A:$I,9,0) -> #N/A | J316: =IF(AND(ISNA(G316),ISNA(I316)),"BOTH #N/A","OK") -> OK | K316: =IFERROR(I316, IFERROR(G316, L316)) -> Corporate IG USD - Other | L316: Corporate IG USD - Other | M316: =_xlfn.IFNA(VLOOKUP(K316,'Mapping DEF'!A:C,2,0),"") -> Spread | N316: =+_xlfn.IFNA(VLOOKUP(M316,'Mapping DEF'!B:C,2,FALSE),"") -> Spread | O316: -30.00bps
A317: CRASH08 | B317: Crash '08 - Absolute, Sep 12 - Nov 03, 2008 | C317: 2310 | D317: Governments relax lockdown measures after successfully containing the COVID-19 outbreak. A moderate recovery in global growth follows a sharp contraction and significant policy easing. | E317: - | G317: =+VLOOKUP(F317,[1]Explore!$B:$I,8,0) -> #N/A | H317: - | I317: =+VLOOKUP(H317,[1]Explore!$A:$I,9,0) -> #N/A | J317: =IF(AND(ISNA(G317),ISNA(I317)),"BOTH #N/A","OK") -> BOTH #N/A | K317: =IFERROR(I317, IFERROR(G317, L317)) -> - | L317: - | M317: =_xlfn.IFNA(VLOOKUP(K317,'Mapping DEF'!A:C,2,0),"") | N317: =+_xlfn.IFNA(VLOOKUP(M317,'Mapping DEF'!B:C,2,FALSE),"")
A318: CREDIT07 | B318: Credit '07 - Relative, Jul 01, 2007 - Jul 01, 2008 | C318: 2307 | D318: Governments relax lockdown measures after successfully containing the COVID-19 outbreak. A moderate recovery in global growth follows a sharp contraction and significant policy easing. | E318: - | G318: =+VLOOKUP(F318,[1]Explore!$B:$I,8,0) -> #N/A | H318: - | I318: =+VLOOKUP(H318,[1]Explore!$A:$I,9,0) -> #N/A | J318: =IF(AND(ISNA(G318),ISNA(I318)),"BOTH #N/A","OK") -> BOTH #N/A | K318: =IFERROR(I318, IFERROR(G318, L318)) -> - | L318: - | M318: =_xlfn.IFNA(VLOOKUP(K318,'Mapping DEF'!A:C,2,0),"") | N318: =+_xlfn.IFNA(VLOOKUP(M318,'Mapping DEF'!B:C,2,FALSE),"")
A319: CVIRUS_GC | B319: Coronavirus - Coronavirus Global Contagion | C319: 2438 | D319: Governments relax lockdown measures after successfully containing the COVID-19 outbreak. A moderate recovery in global growth follows a sharp contraction and significant policy easing. | E319: Tsy 10Y USD_10yr - Yield -30.00 bps, | F319: Tsy 10Y | G319: =+VLOOKUP(F319,[1]Explore!$B:$I,8,0) -> Govt USD | H319: USD_10yr | I319: =+VLOOKUP(H319,[1]Explore!$A:$I,9,0) -> Govt USD | J319: =IF(AND(ISNA(G319),ISNA(I319)),"BOTH #N/A","OK") -> OK | K319: =IFERROR(I319, IFERROR(G319, L319)) -> Govt USD | L319: Yield | M319: =_xlfn.IFNA(VLOOKUP(K319,'Mapping DEF'!A:C,2,0),"") -> Curve (Local) | N319: =+_xlfn.IFNA(VLOOKUP(M319,'Mapping DEF'!B:C,2,FALSE),"") -> Term Structure | O319: -30.00 bps
A320: CVIRUS_GC | B320: Coronavirus - Coronavirus Global Contagion | C320: 2438 | D320: Governments relax lockdown measures after successfully containing the COVID-19 outbreak. A moderate recovery in global growth follows a sharp contraction and significant policy easing. | E320: Brent Crude ICE 1 USD_COMD_CO_1 - Price Level -10.00 pct, | F320: Brent Crude ICE 1 | G320: =+VLOOKUP(F320,[1]Explore!$B:$I,8,0) -> Alternative - Commodity | H320: USD_COMD_CO_1 | I320: =+VLOOKUP(H320,[1]Explore!$A:$I,9,0) -> Alternative - Commodity | J320: =IF(AND(ISNA(G320),ISNA(I320)),"BOTH #N/A","OK") -> OK | K320: =IFERROR(I320, IFERROR(G320, L320)) -> Alternative - Commodity | L320: Price Level | M320: =_xlfn.IFNA(VLOOKUP(K320,'Mapping DEF'!A:C,2,0),"") -> Alternative | N320: =+_xlfn.IFNA(VLOOKUP(M320,'Mapping DEF'!B:C,2,FALSE),"") -> Other | O320: -10.00 pct
A321: CVIRUS_GC | B321: Coronavirus - Coronavirus Global Contagion | C321: 2438 | D321: Governments relax lockdown measures after successfully containing the COVID-19 outbreak. A moderate recovery in global growth follows a sharp contraction and significant policy easing. | E321: Gold COMEX 1 USD_COMD_GC_1 - Price Level 6.00 pct, | F321: Gold COMEX 1 | G321: =+VLOOKUP(F321,[1]Explore!$B:$I,8,0) -> Alternative - Commodity | H321: USD_COMD_GC_1 | I321: =+VLOOKUP(H321,[1]Explore!$A:$I,9,0) -> Alternative - Commodity | J321: =IF(AND(ISNA(G321),ISNA(I321)),"BOTH #N/A","OK") -> OK | K321: =IFERROR(I321, IFERROR(G321, L321)) -> Alternative - Commodity | L321: Price Level | M321: =_xlfn.IFNA(VLOOKUP(K321,'Mapping DEF'!A:C,2,0),"") -> Alternative | N321: =+_xlfn.IFNA(VLOOKUP(M321,'Mapping DEF'!B:C,2,FALSE),"") -> Other | O321: 6.00 pct
A322: CVIRUS_GC | B322: Coronavirus - Coronavirus Global Contagion | C322: 2438 | D322: Governments relax lockdown measures after successfully containing the COVID-19 outbreak. A moderate recovery in global growth follows a sharp contraction and significant policy easing. | E322: MXN 5Y MXN_5yr - Yield 50.00 bps, | F322: MXN 5Y | G322: =+VLOOKUP(F322,[1]Explore!$B:$I,8,0) -> Govt Emerging Markets | H322: MXN_5yr | I322: =+VLOOKUP(H322,[1]Explore!$A:$I,9,0) -> Govt Emerging Markets | J322: =IF(AND(ISNA(G322),ISNA(I322)),"BOTH #N/A","OK") -> OK | K322: =IFERROR(I322, IFERROR(G322, L322)) -> Govt Emerging Markets | L322: Yield | M322: =_xlfn.IFNA(VLOOKUP(K322,'Mapping DEF'!A:C,2,0),"") -> Curve (Local) | N322: =+_xlfn.IFNA(VLOOKUP(M322,'Mapping DEF'!B:C,2,FALSE),"") -> Term Structure | O322: 50.00 bps
A323: CVIRUS_GC | B323: Coronavirus - Coronavirus Global Contagion | C323: 2438 | D323: Governments relax lockdown measures after successfully containing the COVID-19 outbreak. A moderate recovery in global growth follows a sharp contraction and significant policy easing. | E323: ZAR 10Y ZAR_10yr - Yield 100.00 bps, | F323: ZAR 10Y | G323: =+VLOOKUP(F323,[1]Explore!$B:$I,8,0) -> Govt Emerging Markets | H323: ZAR_10yr | I323: =+VLOOKUP(H323,[1]Explore!$A:$I,9,0) -> Govt Emerging Markets | J323: =IF(AND(ISNA(G323),ISNA(I323)),"BOTH #N/A","OK") -> OK | K323: =IFERROR(I323, IFERROR(G323, L323)) -> Govt Emerging Markets | L323: Yield | M323: =_xlfn.IFNA(VLOOKUP(K323,'Mapping DEF'!A:C,2,0),"") -> Curve (Local) | N323: =+_xlfn.IFNA(VLOOKUP(M323,'Mapping DEF'!B:C,2,FALSE),"") -> Term Structure | O323: 100.00 bps
A324: CVIRUS_GC | B324: Coronavirus - Coronavirus Global Contagion | C324: 2438 | D324: Governments relax lockdown measures after successfully containing the COVID-19 outbreak. A moderate recovery in global growth follows a sharp contraction and significant policy easing. | E324: PLN 5Y PLN_5yr - Yield -30.00 bps, | F324: PLN 5Y | G324: =+VLOOKUP(F324,[1]Explore!$B:$I,8,0) -> Govt Emerging Markets | H324: PLN_5yr | I324: =+VLOOKUP(H324,[1]Explore!$A:$I,9,0) -> Govt Emerging Markets | J324: =IF(AND(ISNA(G324),ISNA(I324)),"BOTH #N/A","OK") -> OK | K324: =IFERROR(I324, IFERROR(G324, L324)) -> Govt Emerging Markets | L324: Yield | M324: =_xlfn.IFNA(VLOOKUP(K324,'Mapping DEF'!A:C,2,0),"") -> Curve (Local) | N324: =+_xlfn.IFNA(VLOOKUP(M324,'Mapping DEF'!B:C,2,FALSE),"") -> Term Structure | O324: -30.00 bps
A325: CVIRUS_GC | B325: Coronavirus - Coronavirus Global Contagion | C325: 2438 | D325: Governments relax lockdown measures after successfully containing the COVID-19 outbreak. A moderate recovery in global growth follows a sharp contraction and significant policy easing. | E325: CHF/USD CHF_FX_USD - FX 2.00 pct, | F325: CHFUSD | G325: =+VLOOKUP(F325,[1]Explore!$B:$I,8,0) -> #N/A | H325: CHF_FX_USD | I325: =+VLOOKUP(H325,[1]Explore!$A:$I,9,0) -> Developed Currency | J325: =IF(AND(ISNA(G325),ISNA(I325)),"BOTH #N/A","OK") -> OK | K325: =IFERROR(I325, IFERROR(G325, L325)) -> Developed Currency | L325: FX | M325: =_xlfn.IFNA(VLOOKUP(K325,'Mapping DEF'!A:C,2,0),"") -> FX | N325: =+_xlfn.IFNA(VLOOKUP(M325,'Mapping DEF'!B:C,2,FALSE),"") -> FX | O325: 2.00 pct
A326: CVIRUS_GC | B326: Coronavirus - Coronavirus Global Contagion | C326: 2438 | D326: Credit & liquidity crisis and equity market crash set off by Lehman Brothers bankruptcy. Significant credit spreads widening caused by massive deleveraging. Shocks for DxS Factors are spreads. | E326: CNY/USD CNY_FX_USD - FX -3.50 pct, | F326: CNYUSD | G326: =+VLOOKUP(F326,[1]Explore!$B:$I,8,0) -> #N/A | H326: CNY_FX_USD | I326: =+VLOOKUP(H326,[1]Explore!$A:$I,9,0) -> Emerging Currency | J326: =IF(AND(ISNA(G326),ISNA(I326)),"BOTH #N/A","OK") -> OK | K326: =IFERROR(I326, IFERROR(G326, L326)) -> Emerging Currency | L326: FX | M326: =_xlfn.IFNA(VLOOKUP(K326,'Mapping DEF'!A:C,2,0),"") -> FX | N326: =+_xlfn.IFNA(VLOOKUP(M326,'Mapping DEF'!B:C,2,FALSE),"") -> FX | O326: -3.50 pct
A327: CVIRUS_GC | B327: Coronavirus - Coronavirus Global Contagion | C327: 2438 | D327: Credit & liquidity crisis stemming from a severe slowdown in the housing market causing significant widening of credit spreads and increased implied volatility. Shocks for DxS Factors are percentages of spread. | E327: JPY/USD JPY_FX_USD - FX 3.00 pct, | F327: JPY/USD | G327: =+VLOOKUP(F327,[1]Explore!$B:$I,8,0) -> JPY | H327: JPY_FX_USD | I327: =+VLOOKUP(H327,[1]Explore!$A:$I,9,0) -> JPY | J327: =IF(AND(ISNA(G327),ISNA(I327)),"BOTH #N/A","OK") -> OK | K327: =IFERROR(I327, IFERROR(G327, L327)) -> JPY | L327: FX | M327: =_xlfn.IFNA(VLOOKUP(K327,'Mapping DEF'!A:C,2,0),"") -> FX | N327: =+_xlfn.IFNA(VLOOKUP(M327,'Mapping DEF'!B:C,2,FALSE),"") -> FX | O327: 3.00 pct
A328: CVIRUS_GC | B328: Coronavirus - Coronavirus Global Contagion | C328: 2438 | D328: A hypothetical scenario in which the coronavirus spreads globally, with increasing numbers of infections and deaths beyond China. More cities are placed on lockdown in an attempt to contain the virus, transport systems are closed, and flights are grounded. Reduced economic activity impacts global growth. | E328: TWD/USD TWD_FX_USD - FX -3.00 pct, | F328: TWDUSD | G328: =+VLOOKUP(F328,[1]Explore!$B:$I,8,0) -> #N/A | H328: TWD_FX_USD | I328: =+VLOOKUP(H328,[1]Explore!$A:$I,9,0) -> Emerging Currency | J328: =IF(AND(ISNA(G328),ISNA(I328)),"BOTH #N/A","OK") -> OK | K328: =IFERROR(I328, IFERROR(G328, L328)) -> Emerging Currency | L328: FX | M328: =_xlfn.IFNA(VLOOKUP(K328,'Mapping DEF'!A:C,2,0),"") -> FX | N328: =+_xlfn.IFNA(VLOOKUP(M328,'Mapping DEF'!B:C,2,FALSE),"") -> FX | O328: -3.00 pct
A329: CVIRUS_GC | B329: Coronavirus - Coronavirus Global Contagion | C329: 2438 | D329: A hypothetical scenario in which the coronavirus spreads globally, with increasing numbers of infections and deaths beyond China. More cities are placed on lockdown in an attempt to contain the virus, transport systems are closed, and flights are grounded. Reduced economic activity impacts global growth. | E329: MSCI World Net TR MSCIWLDNET - Index Level -8.00 pct, | F329: MSCI World Net TR | G329: =+VLOOKUP(F329,[1]Explore!$B:$I,8,0) -> Equity Implied Volatility | H329: MSCIWLDNET | I329: =+VLOOKUP(H329,[1]Explore!$A:$I,9,0) -> Equity Implied Volatility | J329: =IF(AND(ISNA(G329),ISNA(I329)),"BOTH #N/A","OK") -> OK | K329: =IFERROR(I329, IFERROR(G329, L329)) -> Equity Implied Volatility | L329: Index Level | M329: =_xlfn.IFNA(VLOOKUP(K329,'Mapping DEF'!A:C,2,0),"") -> Equity Derivatives | N329: =+_xlfn.IFNA(VLOOKUP(M329,'Mapping DEF'!B:C,2,FALSE),"") -> Equity | O329: -8.00 pct
A330: CVIRUS_GC | B330: Coronavirus - Coronavirus Global Contagion | C330: 2438 | D330: A hypothetical scenario in which the coronavirus spreads globally, with increasing numbers of infections and deaths beyond China. More cities are placed on lockdown in an attempt to contain the virus, transport systems are closed, and flights are grounded. Reduced economic activity impacts global growth. | E330: Time ALL_TIME - Time 21.00 days, | F330: Time | G330: =+VLOOKUP(F330,[1]Explore!$B:$I,8,0) -> #N/A | H330: ALL_TIME | I330: =+VLOOKUP(H330,[1]Explore!$A:$I,9,0) -> #N/A | J330: =IF(AND(ISNA(G330),ISNA(I330)),"BOTH #N/A","OK") -> BOTH #N/A | K330: =IFERROR(I330, IFERROR(G330, L330)) -> Time | L330: Time | M330: =_xlfn.IFNA(VLOOKUP(K330,'Mapping DEF'!A:C,2,0),"") -> Time | N330: =+_xlfn.IFNA(VLOOKUP(M330,'Mapping DEF'!B:C,2,FALSE),"") -> Other | O330: 21.00 days
... A719: EU_USPART | B719: EU Carbon Policies - EU/US Partner on CBAM (04/2022) | C719: 2473 | D719: EU/US Partner on CBAM - An unexpected climate alliance formed between the US and the EU leaves China out, and fears of a trade war escalate | E719: MXEU CONSUM DISC(EUR) - MSCI EUROPE(EUR) [MXEU0CD-MXEU] - Index Level -10.00 pct | F719: MXEU CONSUM DISC(EUR) | G719: =+VLOOKUP(F719,[1]Explore!$B:$I,8,0) -> Equity Implied Volatility | H719: DISCEUR | I719: =+VLOOKUP(H719,[1]Explore!$A:$I,9,0) -> #N/A | J719: =IF(AND(ISNA(G719),ISNA(I719)),"BOTH #N/A","OK") -> OK | K719: =IFERROR(I719, IFERROR(G719, L719)) -> Equity Implied Volatility | L719: Index Level | M719: =_xlfn.IFNA(VLOOKUP(K719,'Mapping DEF'!A:C,2,0),"") -> Equity Derivatives | N719: =+_xlfn.IFNA(VLOOKUP(M719,'Mapping DEF'!B:C,2,FALSE),"") -> Equity | O719: -10.00 pct
A720: FED13_ABS | B720: Fed Tapering '13 - Absolute, May 21 - June 24, 2013 | C720: 2316 | D720: Congress Testimony by Bernanke on tapering mortgage purchases caused both equity and bond markets to sell-off. Emerging Markets suffered as expectations of higher US rates caused an unwind in Carry trades. Shocks for DxS Factors are spreads. | E720: - | G720: =+VLOOKUP(F720,[1]Explore!$B:$I,8,0) -> #N/A | H720: - | I720: =+VLOOKUP(H720,[1]Explore!$A:$I,9,0) -> #N/A | J720: =IF(AND(ISNA(G720),ISNA(I720)),"BOTH #N/A","OK") -> BOTH #N/A | K720: =IFERROR(I720, IFERROR(G720, L720)) -> - | L720: - | M720: =_xlfn.IFNA(VLOOKUP(K720,'Mapping DEF'!A:C,2,0),"") | N720: =+_xlfn.IFNA(VLOOKUP(M720,'Mapping DEF'!B:C,2,FALSE),"")
A721: FEDTAP13 | B721: Fed Tapering '13 - Relative, May 21 - June 24, 2013 | C721: 2315 | D721: Congress Testimony by Bernanke on tapering mortgage purchases caused both equity and bond markets to sell-off. Emerging Markets suffered as expectations of higher US rates caused an unwind in Carry trades. Shocks for DxS Factors are percentages of spread. | E721: - | G721: =+VLOOKUP(F721,[1]Explore!$B:$I,8,0) -> #N/A | H721: - | I721: =+VLOOKUP(H721,[1]Explore!$A:$I,9,0) -> #N/A | J721: =IF(AND(ISNA(G721),ISNA(I721)),"BOTH #N/A","OK") -> BOTH #N/A | K721: =IFERROR(I721, IFERROR(G721, L721)) -> - | L721: - | M721: =_xlfn.IFNA(VLOOKUP(K721,'Mapping DEF'!A:C,2,0),"") | N721: =+_xlfn.IFNA(VLOOKUP(M721,'Mapping DEF'!B:C,2,FALSE),"")
A722: FED_CUTS50 | B722: Fed Cuts Rates 50 bps Sep 2025 Scenario | C722: 2111 | D722: The Fed surprises markets by delivering a 50bp rate cut, beyond the expected 25bp first cut, and signals that another cut may still occur later this year. The Fed is acting proactively easing financial conditions to engineer a soft landing rather than a crisis reaction. | E722: Tsy 1Y USD_1yr - Yield -50.00 bps, | F722: Tsy 1Y | G722: =+VLOOKUP(F722,[1]Explore!$B:$I,8,0) -> Govt USD | H722: USD_1yr | I722: =+VLOOKUP(H722,[1]Explore!$A:$I,9,0) -> Govt USD | J722: =IF(AND(ISNA(G722),ISNA(I722)),"BOTH #N/A","OK") -> OK | K722: =IFERROR(I722, IFERROR(G722, L722)) -> Govt USD | L722: Yield | M722: =_xlfn.IFNA(VLOOKUP(K722,'Mapping DEF'!A:C,2,0),"") -> Curve (Local) | N722: =+_xlfn.IFNA(VLOOKUP(M722,'Mapping DEF'!B:C,2,FALSE),"") -> Term Structure | O722: -50.00 bps
A723: FED_CUTS50 | B723: Fed Cuts Rates 50 bps Sep 2025 Scenario | C723: 2111 | D723: The Fed surprises markets by delivering a 50bp rate cut, beyond the expected 25bp first cut, and signals that another cut may still occur later this year. The Fed is acting proactively easing financial conditions to engineer a soft landing rather than a crisis reaction. | E723: Tsy 10Y USD_10yr - Yield -30.00 bps, | F723: Tsy 10Y | G723: =+VLOOKUP(F723,[1]Explore!$B:$I,8,0) -> Govt USD | H723: USD_10yr | I723: =+VLOOKUP(H723,[1]Explore!$A:$I,9,0) -> Govt USD | J723: =IF(AND(ISNA(G723),ISNA(I723)),"BOTH #N/A","OK") -> OK | K723: =IFERROR(I723, IFERROR(G723, L723)) -> Govt USD | L723: Yield | M723: =_xlfn.IFNA(VLOOKUP(K723,'Mapping DEF'!A:C,2,0),"") -> Curve (Local) | N723: =+_xlfn.IFNA(VLOOKUP(M723,'Mapping DEF'!B:C,2,FALSE),"") -> Term Structure | O723: -30.00 bps
A724: FED_CUTS50 | B724: Fed Cuts Rates 50 bps Sep 2025 Scenario | C724: 2111 | D724: The Fed surprises markets by delivering a 50bp rate cut, beyond the expected 25bp first cut, and signals that another cut may still occur later this year. The Fed is acting proactively easing financial conditions to engineer a soft landing rather than a crisis reaction. | E724: USD INF 1Y USD_INF_1yr - Yield 50.00 bps, | F724: USD INF 1Y | G724: =+VLOOKUP(F724,[1]Explore!$B:$I,8,0) -> USD Inflation | H724: USD_INF_1yr | I724: =+VLOOKUP(H724,[1]Explore!$A:$I,9,0) -> USD Inflation | J724: =IF(AND(ISNA(G724),ISNA(I724)),"BOTH #N/A","OK") -> OK | K724: =IFERROR(I724, IFERROR(G724, L724)) -> USD Inflation | L724: Yield | M724: =_xlfn.IFNA(VLOOKUP(K724,'Mapping DEF'!A:C,2,0),"") -> Inflation | N724: =+_xlfn.IFNA(VLOOKUP(M724,'Mapping DEF'!B:C,2,FALSE),"") -> Other | O724: 50.00 bps
A725: FED_CUTS50 | B725: Fed Cuts Rates 50 bps Sep 2025 Scenario | C725: 2111 | D725: The Fed surprises markets by delivering a 50bp rate cut, beyond the expected 25bp first cut, and signals that another cut may still occur later this year. The Fed is acting proactively easing financial conditions to engineer a soft landing rather than a crisis reaction. | E725: USD INF 10Y USD_INF_10yr - Yield 0.00 bps, | F725: USD INF 10Y | G725: =+VLOOKUP(F725,[1]Explore!$B:$I,8,0) -> USD Inflation | H725: USD_INF_10yr | I725: =+VLOOKUP(H725,[1]Explore!$A:$I,9,0) -> USD Inflation | J725: =IF(AND(ISNA(G725),ISNA(I725)),"BOTH #N/A","OK") -> OK | K725: =IFERROR(I725, IFERROR(G725, L725)) -> USD Inflation | L725: Yield | M725: =_xlfn.IFNA(VLOOKUP(K725,'Mapping DEF'!A:C,2,0),"") -> Inflation | N725: =+_xlfn.IFNA(VLOOKUP(M725,'Mapping DEF'!B:C,2,FALSE),"") -> Other | O725: 0.00 bps
A726: FED_CUTS50 | B726: Fed Cuts Rates 50 bps Sep 2025 Scenario | C726: 2111 | D726: The Fed surprises markets by delivering a 50bp rate cut, beyond the expected 25bp first cut, and signals that another cut may still occur later this year. The Fed is acting proactively easing financial conditions to engineer a soft landing rather than a crisis reaction. | E726: Gold COMEX 1 USD_COMD_GC_1 - Price Level 5.00 pct, | F726: Gold COMEX 1 | G726: =+VLOOKUP(F726,[1]Explore!$B:$I,8,0) -> Alternative - Commodity | H726: USD_COMD_GC_1 | I726: =+VLOOKUP(H726,[1]Explore!$A:$I,9,0) -> Alternative - Commodity | J726: =IF(AND(ISNA(G726),ISNA(I726)),"BOTH #N/A","OK") -> OK | K726: =IFERROR(I726, IFERROR(G726, L726)) -> Alternative - Commodity | L726: Price Level | M726: =_xlfn.IFNA(VLOOKUP(K726,'Mapping DEF'!A:C,2,0),"") -> Alternative | N726: =+_xlfn.IFNA(VLOOKUP(M726,'Mapping DEF'!B:C,2,FALSE),"") -> Other | O726: 5.00 pct
A727: FED_CUTS50 | B727: Fed Cuts Rates 50 bps Sep 2025 Scenario | C727: 2111 | D727: The Fed surprises markets by delivering a 50bp rate cut, beyond the expected 25bp first cut, and signals that another cut may still occur later this year. The Fed is acting proactively easing financial conditions to engineer a soft landing rather than a crisis reaction. | E727: US HY Market USD_HY_MARKET_SF - Spread Yield -30.00 bps, | F727: US HY Market | G727: =+VLOOKUP(F727,[1]Explore!$B:$I,8,0) -> Corporate HY USD - Other | H727: USD_HY_MARKET_SF | I727: =+VLOOKUP(H727,[1]Explore!$A:$I,9,0) -> Corporate HY USD - Other | J727: =IF(AND(ISNA(G727),ISNA(I727)),"BOTH #N/A","OK") -> OK | K727: =IFERROR(I727, IFERROR(G727, L727)) -> Corporate HY USD - Other | L727: Spread Yield | M727: =_xlfn.IFNA(VLOOKUP(K727,'Mapping DEF'!A:C,2,0),"") -> Spread | N727: =+_xlfn.IFNA(VLOOKUP(M727,'Mapping DEF'!B:C,2,FALSE),"") -> Spread | O727: -30.00 bps
A728: FED_CUTS50 | B728: Fed Cuts Rates 50 bps Sep 2025 Scenario | C728: 2111 | D728: The Fed surprises markets by delivering a 50bp rate cut, beyond the expected 25bp first cut, and signals that another cut may still occur later this year. The Fed is acting proactively easing financial conditions to engineer a soft landing rather than a crisis reaction. | E728: S&P 500 Consumer Staples Index SPCS - Index Level 10.00 pct, | F728: S&P 500 Consumer Staples Index | G728: =+VLOOKUP(F728,[1]Explore!$B:$I,8,0) -> Other - Index | H728: SPCS | I728: =+VLOOKUP(H728,[1]Explore!$A:$I,9,0) -> Other - Index | J728: =IF(AND(ISNA(G728),ISNA(I728)),"BOTH #N/A","OK") -> OK | K728: =IFERROR(I728, IFERROR(G728, L728)) -> Other - Index | L728: Index Level | M728: =_xlfn.IFNA(VLOOKUP(K728,'Mapping DEF'!A:C,2,0),"") -> Other | N728: =+_xlfn.IFNA(VLOOKUP(M728,'Mapping DEF'!B:C,2,FALSE),"") -> Other | O728: 10.00 pct
A729: FED_CUTS50 | B729: Fed Cuts Rates 50 bps Sep 2025 Scenario | C729: 2111 | D729: The Fed surprises markets by delivering a 50bp rate cut, beyond the expected 25bp first cut, and signals that another cut may still occur later this year. The Fed is acting proactively easing financial conditions to engineer a soft landing rather than a crisis reaction. | E729: S&P 500 Information Technology SPIT - Index Level 15.00 pct | F729: S&P 500 Information Technology | G729: =+VLOOKUP(F729,[1]Explore!$B:$I,8,0) -> Other - Index | H729: SPIT | I729: =+VLOOKUP(H729,[1]Explore!$A:$I,9,0) -> Other - Index | J729: =IF(AND(ISNA(G729),ISNA(I729)),"BOTH #N/A","OK") -> OK | K729: =IFERROR(I729, IFERROR(G729, L729)) -> Other - Index | L729: Index Level | M729: =_xlfn.IFNA(VLOOKUP(K729,'Mapping DEF'!A:C,2,0),"") -> Other | N729: =+_xlfn.IFNA(VLOOKUP(M729,'Mapping DEF'!B:C,2,FALSE),"") -> Other | O729: 15.00 pct
A730: FED_GEO | B730: Fed Interest Rate Regimes - Growth Concerns | C730: 2419 | D730: Growth Concerns : Tail risks, such as geopolitical and macroeconomic concerns, cause the Fed to adopt a more dovish stance. | E730: Tsy 2Y USD_2yr - Yield -50.00 bps, | F730: Tsy 2Y | G730: =+VLOOKUP(F730,[1]Explore!$B:$I,8,0) -> Govt USD | H730: USD_2yr | I730: =+VLOOKUP(H730,[1]Explore!$A:$I,9,0) -> Govt USD | J730: =IF(AND(ISNA(G730),ISNA(I730)),"BOTH #N/A","OK") -> OK | K730: =IFERROR(I730, IFERROR(G730, L730)) -> Govt USD | L730: Yield | M730: =_xlfn.IFNA(VLOOKUP(K730,'Mapping DEF'!A:C,2,0),"") -> Curve (Local) | N730: =+_xlfn.IFNA(VLOOKUP(M730,'Mapping DEF'!B:C,2,FALSE),"") -> Term Structure | O730: -50.00 bps
A731: FED_GEO | B731: Fed Interest Rate Regimes - Growth Concerns | C731: 2419 | D731: Growth Concerns : Tail risks, such as geopolitical and macroeconomic concerns, cause the Fed to adopt a more dovish stance. | E731: Tsy 10Y USD_10yr - Yield -40.00 bps, | F731: Tsy 10Y | G731: =+VLOOKUP(F731,[1]Explore!$B:$I,8,0) -> Govt USD | H731: USD_10yr | I731: =+VLOOKUP(H731,[1]Explore!$A:$I,9,0) -> Govt USD | J731: =IF(AND(ISNA(G731),ISNA(I731)),"BOTH #N/A","OK") -> OK | K731: =IFERROR(I731, IFERROR(G731, L731)) -> Govt USD | L731: Yield | M731: =_xlfn.IFNA(VLOOKUP(K731,'Mapping DEF'!A:C,2,0),"") -> Curve (Local) | N731: =+_xlfn.IFNA(VLOOKUP(M731,'Mapping DEF'!B:C,2,FALSE),"") -> Term Structure | O731: -40.00 bps
A732: FED_GEO | B732: Fed Interest Rate Regimes - Growth Concerns | C732: 2419 | D732: Growth Concerns : Tail risks, such as geopolitical and macroeconomic concerns, cause the Fed to adopt a more dovish stance. | E732: DXY DXY - Index Level -5.00 pct, | F732: DXY | G732: =+VLOOKUP(F732,[1]Explore!$B:$I,8,0) -> #N/A | H732: DXY | I732: =+VLOOKUP(H732,[1]Explore!$A:$I,9,0) -> #N/A | J732: =IF(AND(ISNA(G732),ISNA(I732)),"BOTH #N/A","OK") -> BOTH #N/A | K732: =IFERROR(I732, IFERROR(G732, L732)) -> Dollar Index | L732: Dollar Index | M732: =_xlfn.IFNA(VLOOKUP(K732,'Mapping DEF'!A:C,2,0),"") -> Index Level | N732: =+_xlfn.IFNA(VLOOKUP(M732,'Mapping DEF'!B:C,2,FALSE),"") -> Other | O732: -5.00 pct
A733: FED_GEO | B733: Fed Interest Rate Regimes - Growth Concerns | C733: 2419 | D733: Growth Concerns : Tail risks, such as geopolitical and macroeconomic concerns, cause the Fed to adopt a more dovish stance. | E733: S&P 500 SPX - Index Level -10.00 pct, | F733: S&P 500 | G733: =+VLOOKUP(F733,[1]Explore!$B:$I,8,0) -> Equity Implied Volatility | H733: SPX | I733: =+VLOOKUP(H733,[1]Explore!$A:$I,9,0) -> Equity Implied Volatility | J733: =IF(AND(ISNA(G733),ISNA(I733)),"BOTH #N/A","OK") -> OK | K733: =IFERROR(I733, IFERROR(G733, L733)) -> Equity Implied Volatility | L733: Index Level | M733: =_xlfn.IFNA(VLOOKUP(K733,'Mapping DEF'!A:C,2,0),"") -> Equity Derivatives | N733: =+_xlfn.IFNA(VLOOKUP(M733,'Mapping DEF'!B:C,2,FALSE),"") -> Equity | O733: -10.00 pct
... A744: FED_HOLDS | B744: Fed Hold Rates Sep 2025 Scenario | C744: 2110 | D744: The Fed decides to maintain the current policy rate at its existing level, foregoing the widely anticipated 25bps cut. This signals a potential pause for the remainder of the year, emphasizing the Fed commitment to fighting sticky inflation. | E744: US HY Market USD_HY_MARKET_SF - Spread Yield 75.00 bps, | F744: US HY Market | G744: =+VLOOKUP(F744,[1]Explore!$B:$I,8,0) -> Corporate HY USD - Other | H744: USD_HY_MARKET_SF | I744: =+VLOOKUP(H744,[1]Explore!$A:$I,9,0) -> Corporate HY USD - Other | J744: =IF(AND(ISNA(G744),ISNA(I744)),"BOTH #N/A","OK") -> OK | K744: =IFERROR(I744, IFERROR(G744, L744)) -> Corporate HY USD - Other | L744: Spread Yield | M744: =_xlfn.IFNA(VLOOKUP(K744,'Mapping DEF'!A:C,2,0),"") -> Spread | N744: =+_xlfn.IFNA(VLOOKUP(M744,'Mapping DEF'!B:C,2,FALSE),"") -> Spread | O744: 75.00 bps
...

Sheet Sheet11
A1: MAPPING_DEF | B1: Mapping 1 Livello | C1: Mapping 2 Livello | F1: MAPPING_DEF_1 LIV | K1: Mapping 3 livello | L1: Mapping 2 livello | M1: Mapping 1 Livello
A2: Equity Implied Volatility | B2: Equity Derivatives | C2: Equity | F2: Equity Derivatives | K2: Govt USD | L2: =+VLOOKUP(K2,A:B,2,FALSE) -> Curve (Local) | M2: =+VLOOKUP(L2,B:C,2,FALSE) -> Term Structure
A3: Govt USD | B3: Curve (Local) | C3: Term Structure | F3: Curve (Local) | K3: Equity Implied Volatility | L3: =+VLOOKUP(K3,A:B,2,FALSE) -> Equity Derivatives | M3: =+VLOOKUP(L3,B:C,2,FALSE) -> Equity
A4: Emerging Currency | B4: FX | C4: FX | F4: Alternative | K4: Alternative - Commodity | L4: =+VLOOKUP(K4,A:B,2,FALSE) -> Alternative | M4: Other
A5: Industrials | B5: Industry Allocation | C5: Equity | F5: Spread | K5: Emerging Currency | L5: =+VLOOKUP(K5,A:B,2,FALSE) -> FX | M5: =+VLOOKUP(L5,B:C,2,FALSE) -> FX
A6: Alternative - Commodity | B6: Alternative | C6: Alternative | F6: FX | K6: Industrials | L6: =+VLOOKUP(K6,A:B,2,FALSE) -> Industry Allocation | M6: =+VLOOKUP(L6,B:C,2,FALSE) -> Equity
A7: Information Technology | B7: Industry Allocation | C7: Equity | F7: Industry Allocation | K7: Information Technology | L7: =+VLOOKUP(K7,A:B,2,FALSE) -> Industry Allocation | M7: =+VLOOKUP(L7,B:C,2,FALSE) -> Equity
A8: Corporate HY USD - Industry | B8: Spread | C8: Spread | F8: Industry Return | K8: Corporate HY USD - Industry | L8: =+VLOOKUP(K8,A:B,2,FALSE) -> Spread | M8: =+VLOOKUP(L8,B:C,2,FALSE) -> Spread
A9: Industry Return | B9: =A9 -> Industry Return | C9: Equity | F9: Inflation | K9: Industry Return | L9: =+VLOOKUP(K9,A:B,2,FALSE) -> Industry Return | M9: =+VLOOKUP(L9,B:C,2,FALSE) -> Equity
A10: USD Inflation | B10: Inflation | C10: Inflation | F10: Other | K10: USD Inflation | L10: =+VLOOKUP(K10,A:B,2,FALSE) -> Inflation | M10: Other
A11: Govt EUR (Ger) | B11: Curve (Local) | C11: Term Structure | F11: Time | K11: Govt EUR (Ger) | L11: =+VLOOKUP(K11,A:B,2,FALSE) -> Curve (Local) | M11: =+VLOOKUP(L11,B:C,2,FALSE) -> Term Structure
A12: Govt Developed Other (AU, GB, JP, ...) | B12: Curve (Local) | C12: Term Structure | F12: Index Level | K12: Govt Developed Other (AU, GB, JP, ...) | L12: =+VLOOKUP(K12,A:B,2,FALSE) -> Curve (Local) | M12: =+VLOOKUP(L12,B:C,2,FALSE) -> Term Structure
A13: JPY | B13: FX | C13: FX | F13: Country Allocation | K13: JPY | L13: =+VLOOKUP(K13,A:B,2,FALSE) -> FX | M13: =+VLOOKUP(L13,B:C,2,FALSE) -> FX
A14: Other - Index | B14: Other | C14: Other | F14: Spread Govt | K14: Other - Index | L14: =+VLOOKUP(K14,A:B,2,FALSE) -> Other | M14: =+VLOOKUP(L14,B:C,2,FALSE) -> Other
A15: EUR | B15: FX | C15: FX | F15: Style | K15: EUR | L15: =+VLOOKUP(K15,A:B,2,FALSE) -> FX | M15: =+VLOOKUP(L15,B:C,2,FALSE) -> FX
A16: GBP | B16: FX | C16: FX | F16: Spread Yield | K16: GBP | L16: =+VLOOKUP(K16,A:B,2,FALSE) -> FX | M16: =+VLOOKUP(L16,B:C,2,FALSE) -> FX
A17: Time | B17: Time | C17: Time | F17: Commodity | K17: Corporate IG Other - Other | L17: =+VLOOKUP(K17,A:B,2,FALSE) -> Spread | M17: =+VLOOKUP(L17,B:C,2,FALSE) -> Spread
A18: Corporate IG Other - Other | B18: Spread | C18: Spread | F18: Style Return | K18: Time | L18: =+VLOOKUP(K18,A:B,2,FALSE) -> Time | M18: Other
A19: Index Level | B19: =A19 -> Index Level | C19: Dollar Index | F19: Yield | K19: Spread - Municipals | L19: =+VLOOKUP(K19,A:B,2,FALSE) -> Spread | M19: =+VLOOKUP(L19,B:C,2,FALSE) -> Spread
A20: Spread - Municipals | B20: Spread | C20: Spread | F20: Price Level | K20: Index Level | L20: =+VLOOKUP(K20,A:B,2,FALSE) -> Index Level | M20: Other
A21: Health Care | B21: Industry Allocation | C21: Equity | F21: Rates Implied Volatility | K21: Health Care | L21: =+VLOOKUP(K21,A:B,2,FALSE) -> Industry Allocation | M21: =+VLOOKUP(L21,B:C,2,FALSE) -> Equity
A22: Corporate HY USD - Other | B22: Spread | C22: Spread | K22: Utilities | L22: =+VLOOKUP(K22,A:B,2,FALSE) -> Industry Allocation | M22: =+VLOOKUP(L22,B:C,2,FALSE) -> Equity
A23: Utilities | B23: Industry Allocation | C23: Equity | K23: Corporate HY USD - Other | L23: =+VLOOKUP(K23,A:B,2,FALSE) -> Spread | M23: =+VLOOKUP(L23,B:C,2,FALSE) -> Spread
A24: Consumer Discretionary | B24: Industry Allocation | C24: Equity | K24: Consumer Discretionary | L24: =+VLOOKUP(K24,A:B,2,FALSE) -> Industry Allocation | M24: =+VLOOKUP(L24,B:C,2,FALSE) -> Equity
A25: Mortgage Basis | B25: Alternative | C25: Alternative | K25: Mortgage Basis | L25: =+VLOOKUP(K25,A:B,2,FALSE) -> Alternative | M25: Other
A26: Corporate IG USD - Other | B26: Spread | C26: Spread | K26: Corporate IG USD - Other | L26: =+VLOOKUP(K26,A:B,2,FALSE) -> Spread | M26: =+VLOOKUP(L26,B:C,2,FALSE) -> Spread
A27: ABS - Swap Spread | B27: Alternative | C27: Alternative | K27: ABS - Swap Spread | L27: =+VLOOKUP(K27,A:B,2,FALSE) -> Alternative | M27: Other
A28: Mortgage | B28: Alternative | C28: Alternative | K28: Mortgage | L28: =+VLOOKUP(K28,A:B,2,FALSE) -> Alternative | M28: Other
A29: Materials | B29: Industry Allocation | C29: Equity | K29: Materials | L29: =+VLOOKUP(K29,A:B,2,FALSE) -> Industry Allocation | M29: =+VLOOKUP(L29,B:C,2,FALSE) -> Equity
A30: Spread Emerging Markets - Country | B30: Spread | C30: Spread | K30: Spread Emerging Markets - Country | L30: =+VLOOKUP(K30,A:B,2,FALSE) -> Spread | M30: =+VLOOKUP(L30,B:C,2,FALSE) -> Spread
A31: Govt Emerging Markets | B31: Curve (Local) | C31: Term Structure | K31: Spread Govt ITA | L31: =+VLOOKUP(K31,A:B,2,FALSE) -> Spread Govt | M31: =+VLOOKUP(L31,B:C,2,FALSE) -> Term Structure
A32: Consumer Staples | B32: Industry Allocation | C32: Equity | K32: Govt Emerging Markets | L32: =+VLOOKUP(K32,A:B,2,FALSE) -> Curve (Local) | M32: =+VLOOKUP(L32,B:C,2,FALSE) -> Term Structure
A33: Spread Govt ITA | B33: Spread Govt | C33: Term Structure | K33: Emerging Markets | L33: =+VLOOKUP(K33,A:B,2,FALSE) -> Country Allocation | M33: =+VLOOKUP(L33,B:C,2,FALSE) -> Equity
A34: Emerging Markets | B34: Country Allocation | C34: Equity | K34: Other - Spread Yield | L34: =+VLOOKUP(K34,A:B,2,FALSE) -> Other | M34: =+VLOOKUP(L34,B:C,2,FALSE) -> Other
A35: Other - Spread Yield | B35: Other | C35: Other | K35: Consumer Staples | L35: =+VLOOKUP(K35,A:B,2,FALSE) -> Industry Allocation | M35: =+VLOOKUP(L35,B:C,2,FALSE) -> Equity
A36: Real Estate | B36: Industry Allocation | C36: Equity | K36: Corporate HY Other - Maturity | L36: =+VLOOKUP(K36,A:B,2,FALSE) -> Spread | M36: =+VLOOKUP(L36,B:C,2,FALSE) -> Spread
A37: Developed Currency | B37: FX | C37: FX | K37: Corporate IG USD - Industry | L37: =+VLOOKUP(K37,A:B,2,FALSE) -> Spread | M37: =+VLOOKUP(L37,B:C,2,FALSE) -> Spread
A38: Corporate HY Other - Maturity | B38: Spread | C38: Spread | K38: Local Styles | L38: =+VLOOKUP(K38,A:B,2,FALSE) -> Style | M38: =+VLOOKUP(L38,B:C,2,FALSE) -> Equity
A39: Local Styles | B39: Style | C39: Equity | K39: Corporate HY EUR - Industry | L39: =+VLOOKUP(K39,A:B,2,FALSE) -> Spread | M39: =+VLOOKUP(L39,B:C,2,FALSE) -> Spread
A40: Corporate HY EUR - Industry | B40: Spread | C40: Spread | K40: Real Estate | L40: =+VLOOKUP(K40,A:B,2,FALSE) -> Industry Allocation | M40: =+VLOOKUP(L40,B:C,2,FALSE) -> Equity
... A44: Value | B44: Style | C44: Equity | K44: Value | L44: =+VLOOKUP(K44,A:B,2,FALSE) -> Style | M44: =+VLOOKUP(L44,B:C,2,FALSE) -> Equity
A45: Alternative - Index | B45: Alternative | C45: Alternative | K45: Alternative - Index | L45: =+VLOOKUP(K45,A:B,2,FALSE) -> Alternative | M45: Other
A46: EUR Inflation | B46: Inflation | C46: Inflation | K46: EUR Inflation | L46: =+VLOOKUP(K46,A:B,2,FALSE) -> Inflation | M46: Other
A47: Corporate IG USD - Market | B47: Spread | C47: Spread | K47: Corporate IG USD - Market | L47: =+VLOOKUP(K47,A:B,2,FALSE) -> Spread | M47: =+VLOOKUP(L47,B:C,2,FALSE) -> Spread
A48: Spread Govt Peripheral EUR (ex ITA) | B48: Spread Govt | C48: Term Structure | K48: Spread Yield | L48: =+VLOOKUP(K48,A:B,2,FALSE) -> Spread Yield | M48: =+VLOOKUP(L48,B:C,2,FALSE) -> Spread
A49: Spread Yield | B49: =A49 -> Spread Yield | C49: Spread | K49: Spread Govt Peripheral EUR (ex ITA) | L49: =+VLOOKUP(K49,A:B,2,FALSE) -> Spread Govt | M49: =+VLOOKUP(L49,B:C,2,FALSE) -> Term Structure
A50: Other - Inflation | B50: Other | C50: Other | K50: Commodity | L50: =+VLOOKUP(K50,A:B,2,FALSE) -> Alternative | M50: Other
A51: Market | B51: Style | C51: Equity | K51: Other - Inflation | L51: =+VLOOKUP(K51,A:B,2,FALSE) -> Other | M51: =+VLOOKUP(L51,B:C,2,FALSE) -> Other
A52: Commodity | B52: Alternative | C52: Alternative | K52: Market | L52: =+VLOOKUP(K52,A:B,2,FALSE) -> Style | M52: =+VLOOKUP(L52,B:C,2,FALSE) -> Equity
A53: Corporate IG Other - Industry | B53: Spread | C53: Spread | K53: Corporate IG Other - Industry | L53: =+VLOOKUP(K53,A:B,2,FALSE) -> Spread | M53: =+VLOOKUP(L53,B:C,2,FALSE) -> Spread
A54: Volatility | B54: Style | C54: Equity | K54: Volatility | L54: =+VLOOKUP(K54,A:B,2,FALSE) -> Style | M54: =+VLOOKUP(L54,B:C,2,FALSE) -> Equity
A55: Money Market | B55: Other | C55: Other | K55: Money Market | L55: =+VLOOKUP(K55,A:B,2,FALSE) -> Other | M55: =+VLOOKUP(L55,B:C,2,FALSE) -> Other
A56: Yield | B56: =A56 -> Yield | K56: Corporate IG EUR - Industry | L56: =+VLOOKUP(K56,A:B,2,FALSE) -> Spread | M56: =+VLOOKUP(L56,B:C,2,FALSE) -> Spread
A57: Price Level | B57: =A57 -> Price Level | K57: Other - KRD | L57: =+VLOOKUP(K57,A:B,2,FALSE) -> Other | M57: =+VLOOKUP(L57,B:C,2,FALSE) -> Other
A58: Energy | B58: Industry Allocation | K58: Corporate IG EUR - Country | L58: =+VLOOKUP(K58,A:B,2,FALSE) -> Spread | M58: =+VLOOKUP(L58,B:C,2,FALSE) -> Spread
A59: Corporate IG EUR - Industry | B59: Spread | K59: Spread Govt Quasi-Core EUR | L59: =+VLOOKUP(K59,A:B,2,FALSE) -> Spread Govt | M59: =+VLOOKUP(L59,B:C,2,FALSE) -> Term Structure
A60: Other - KRD | B60: Other | K60: Momentum | L60: =+VLOOKUP(K60,A:B,2,FALSE) -> Style | M60: =+VLOOKUP(L60,B:C,2,FALSE) -> Equity
A61: Corporate IG EUR - Country | B61: Spread | K61: Energy | L61: =+VLOOKUP(K61,A:B,2,FALSE) -> Industry Allocation | M61: =+VLOOKUP(L61,B:C,2,FALSE) -> Equity
A62: Spread Govt Quasi-Core EUR | B62: Spread Govt | K62: Rates Implied Volatility | L62: =+VLOOKUP(K62,A:B,2,FALSE) -> Rates Implied Volatility | M62: Other
A63: Momentum | B63: Style | K63: Time | L63: =+VLOOKUP(K63,A:B,2,FALSE) -> Time | M63: Other
A64: Spread Yield | B64: Spread Yield | K64: Corporate HY EUR - Other | L64: =+VLOOKUP(K64,A:B,2,FALSE) -> Spread | M64: =+VLOOKUP(L64,B:C,2,FALSE) -> Spread
K65: Corporate IG Other - Maturity | L65: =+VLOOKUP(K65,A:B,2,FALSE) -> Spread | M65: =+VLOOKUP(L65,B:C,2,FALSE) -> Spread
A66: Rates Implied Volatility | B66: Rates Implied Volatility | K66: Alternative - Hedge Fund | L66: =+VLOOKUP(K66,A:B,2,FALSE) -> Alternative | M66: Other
A67: Time | B67: Time | K67: Financials | L67: =+VLOOKUP(K67,A:B,2,FALSE) -> Industry Allocation | M67: =+VLOOKUP(L67,B:C,2,FALSE) -> Equity
A68: Index Level | B68: Index Level | K68: Agency / Supranational | L68: =+VLOOKUP(K68,A:B,2,FALSE) -> Spread | M68: =+VLOOKUP(L68,B:C,2,FALSE) -> Spread
A69: Corporate HY EUR - Other | B69: Spread | K69: Mortgage - Moneyness | L69: =+VLOOKUP(K69,A:B,2,FALSE) -> Alternative | M69: Other
A70: Corporate IG Other - Maturity | B70: Spread | K70: Size | L70: =+VLOOKUP(K70,A:B,2,FALSE) -> Style | M70: =+VLOOKUP(L70,B:C,2,FALSE) -> Equity
A71: Alternative - Hedge Fund | B71: Alternative | K71: North America | L71: =+VLOOKUP(K71,A:B,2,FALSE) -> Country Allocation | M71: =+VLOOKUP(L71,B:C,2,FALSE) -> Equity
A72: Financials | B72: Industry Allocation | K72: Corporate HY USD - Maturity | L72: =+VLOOKUP(K72,A:B,2,FALSE) -> Spread | M72: =+VLOOKUP(L72,B:C,2,FALSE) -> Spread
A73: Agency / Supranational | B73: Spread
A74: Mortgage - Moneyness | B74: Alternative
A75: Size | B75: Style
A76: North America | B76: Country Allocation
A77: Corporate HY USD - Maturity | B77: Spread

Sheet Pivot
A1: Stress_Scenarios | B1: Mapping 1 Livello | C1: Mapping 2 livello | D1: Mapping 3 livello | E1: Shock_Value | F1: Unnamed: 6
A2: 1995_MCADJ | B2: Equity | C2: Equity Derivatives | D2: Equity Implied Volatility | E2: 17.00pct | F2: SP500 Consum Discr S5COND - Index Level: 17.00pct,
A3: 1995_MCADJ | B3: Equity | C3: Equity Derivatives | D3: Equity Implied Volatility | E3: 24.00pct | F3: SP500 Consum Stapl S5CONS - Index Level: 24.00pct,
A4: 1995_MCADJ | B4: Equity | C4: Equity Derivatives | D4: Equity Implied Volatility | E4: 26.00pct | F4: S&P 500 Industrials S5INDU - Index Level: 26.00pct,
A5: 1995_MCADJ | B5: Equity | C5: Equity Derivatives | D5: Equity Implied Volatility | E5: 29.00pct | F5: S&P 500 Energy S5ENRS - Index Level: 29.00pct,
A6: 1995_MCADJ | B6: Equity | C6: Equity Derivatives | D6: Equity Implied Volatility | E6: 29.00pct | F6: S&P 500 Technology S5INFT - Index Level: 29.00pct,
A7: 1995_MCADJ | B7: Equity | C7: Equity Derivatives | D7: Equity Implied Volatility | E7: 32.00pct | F7: S&P Mid Cap MID - Index Level: 32.00pctc,
A8: 1995_MCADJ | B8: Equity | C8: Equity Derivatives | D8: Equity Implied Volatility | E8: 33.00pct | F8: S&P 500 Health Care S5HLTH - Index Level: 33.00pct,
A9: 1995_MCADJ | B9: Equity | C9: Equity Derivatives | D9: Equity Implied Volatility | E9: 37.00pct | F9: S&P 500 Utilities S5UTIL - Index Level: 37.00pct,
A10: 1995_MCADJ | B10: Equity | C10: Equity Derivatives | D10: Equity Implied Volatility | E10: 38.00pct | F10: S&P 500 Financials S5FINL - Index Level: 38.00pct,
A11: 1995_MCADJ | B11: Equity | C11: Equity Derivatives | D11: Equity Implied Volatility | E11: 47.00pct | F11: S&P Small Cap SML - Index Level: 47.00pct
A12: 1995_MCADJ | B12: Equity | C12: Equity Derivatives | D12: Equity Implied Volatility | E12: 49.00pct | F12: SP500 Communications S5TELS - Index Level: 49.00pct,
... A81: BTAX_COMP | B81: Term Structure | C81: Curve (Local) | D81: Govt USD | E81: 20.00bps | F81: Tsy 10Y USD_10yr - Yield: 20.00bps,
A82: C07_ABS | D82: - | E82: (blank) | F82: -
A83: C08_REL | D83: - | E83: (blank) | F83: -
A84: CB_OVER | B84: Equity | C84: Equity Derivatives | D84: Equity Implied Volatility | E84: -8.00pct | F84: S&P 500 SPX - Index Level: -8.00pct,
A85: CB_OVER | B85: Other | C85: Alternative | D85: Alternative - Commodity | E85: 5.00pct | F85: Gold COMEX 1 USD_COMD_GC_1 - Price Level: 5.00pct,
A86: CB_OVER | B86: Other | C86: Alternative | D86: Alternative - Commodity | E86: 7.00pct | F86: Brent Crude ICE 1 USD_COMD_CO_1 - Price Level: 7.00pct,
A87: CB_OVER | B87: Other | C87: Alternative | D87: Mortgage Basis | E87: 20.00bps | F87: 15yr Mtg Tsy Basis USD_mtg15_tsy - Mortgage Basis: 20.00bps,
A88: CB_OVER | B88: Other | C88: Index Level | D88: Dollar Index | E88: 3.00pct | F88: DXY DXY - Index Level: 3.00pct,
A89: CB_OVER | B89: Other | C89: Inflation | D89: USD Inflation | E89: -50.00bps | F89: USD INF 10Y USD_INF_10yr - Yield: -50.00bps,
A90: CB_OVER | B90: Other | C90: Other | D90: Other - Index | E90: 10.00pct | F90: S&P 500 Consumer Staples Index - S&P 500 [SPCS-SPX] - Index Level: 10.00pct
A91: CB_OVER | B91: Other | C91: Time | D91: Time | E91: 30.00days | F91: Time ALL_TIME - Time: 30.00days,
A92: CB_OVER | B92: Spread | C92: Spread | D92: Corporate HY USD - Other | E92: 50.00bps | F92: US HY Market USD_HY_MARKET - Spread Yield: 50.00bps,
A93: CB_OVER | B93: Spread | C93: Spread | D93: Corporate IG USD - Other | E93: 20.00bps | F93: US Cash Bonds IG USD_LEH_CREDIT3 - Spread Yield: 20.00bps,
A94: CB_OVER | B94: Term Structure | C94: Curve (Local) | D94: Govt USD | E94: 20.00bps | F94: Tsy 2Y USD_2yr - Yield: 20.00bps,
A95: CB_OVER | B95: Term Structure | C95: Curve (Local) | D95: Govt USD | E95: 45.00bps | F95: Tsy 10Y USD_10yr - Yield: 45.00bps,
... A134: CEM_ASIA | B134: Term Structure | C134: Curve (Local) | D134: Govt USD | E134: -20.00bps | F134: Tsy 10Y USD_10yr - Yield -20.00 bps,
A135: CEM_LATAM | D135: Other - Spread Yield | E135: 200.00bps | F135: Middle East and Africa USD_EM_CORP_MIDAF - Spread Yield 200.00 bps
A136: CEM_LATAM | B136: Equity | C136: Country Allocation | D136: Emerging Markets | E136: -10.00pct | F136: Saudi Arabia FMI_WRLD_SAU - Country Return -10.00 pct,
A137: CEM_LATAM | B137: Equity | C137: Equity Derivatives | D137: Equity Implied Volatility | E137: -10.00pct | F137: MSCI EUROPE(EUR) MXEU - Index Level -10.00 pct,
A138: CEM_LATAM | B138: Equity | C138: Equity Derivatives | D138: Equity Implied Volatility | E138: 30.00pct | F138: VIX VIX - Index Level 30.00 pct,
A139: CEM_LATAM | B139: Equity | C139: Industry Allocation | D139: Consumer Discretionary | E139: -15.00pct | F139: Hotels Restaurants & Leisure FMI_EMEA_CDIHOTREST - Industry Return -15.00 pct,
A140: CEM_LATAM | B140: Equity | C140: Industry Allocation | D140: Consumer Staples | E140: 10.00pct | F140: Cons Staples x Alcohol & Tob FMI_LATC_CSTXALCTOB - Industry Return 10.00 pct,
A141: CEM_LATAM | B141: Equity | C141: Industry Allocation | D141: Financials | E141: -10.00pct | F141: Banks FMI_LATC_FINBANK - Industry Return -10.00 pct,
A142: CEM_LATAM | B142: FX | C142: FX | D142: Emerging Currency | E142: -10.00pct | F142: RUB/USD RUB_FX_USD - FX -10.00 pct,
A143: CEM_LATAM | B143: FX | C143: FX | D143: Emerging Currency | E143: -20.00pct | F143: BRL/USD BRL_FX_USD - FX -20.00 pct,
A144: CEM_LATAM | B144: FX | C144: FX | D144: Emerging Currency | E144: -5.00pct | F144: CZK/USD CZK_FX_USD - FX -5.00 pct,
A145: CEM_LATAM | B145: Other | C145: Alternative | D145: Alternative - Commodity | E145: -30.00pct | F145: Brent Crude ICE 1 USD_COMD_CO_1 - Price Level -30.00 pct,
A146: CEM_LATAM | B146: Other | C146: Index Level | D146: Dollar Index | E146: 3.00pct | F146: DXY DXY - Index Level 3.00 pct,
A147: CEM_LATAM | B147: Other | C147: Other | D147: Other - Index | E147: -20.00pct | F147: MSCI EM Latin America (Loc) MS_LA_LCL - Index Level -20.00 pct,
... A156: CEM_LATAM | B156: Term Structure | C156: Spread Govt | D156: Spread Govt ITA | E156: 80.00bps | F156: ITL 10Y ITL_10yr - Spread Yield 80.00 bps,
A157: CHINA15A | D157: - | E157: (blank) | F157: -
A158: CHINA15R | D158: - | E158: (blank) | F158: -
A159: CHN_CPMISS | B159: Equity | C159: Equity Derivatives | D159: Equity Implied Volatility | E159: -4.00pct | F159: MSCI World Net TR MSCIWLDNET - Index Level -4.00 pct,
A160: CHN_CPMISS | B160: Equity | C160: Industry Allocation | D160: Energy | E160: -4.00pct | F160: Energy FMI_APXJ_EGYENERGY - Industry Return -4.00 pct,
A161: CHN_CPMISS | B161: Equity | C161: Industry Allocation | D161: Industrials | E161: -5.00pct | F161: Industrial Conglomerates FMI_APXJ_INDCONGLOM - Industry Return -5.00 pct,
A162: CHN_CPMISS | B162: Equity | C162: Industry Allocation | D162: Materials | E162: -5.00pct | F162: Construction Materials FMI_APXJ_MATCONSTM - Industry Return -5.00 pct,
A163: CHN_CPMISS | B163: Equity | C163: Industry Allocation | D163: Real Estate | E163: -3.00pct | F163: Real Estate Management & Dev FMI_APXJ_FINREALMGT - Industry Return -3.00 pct,
A164: CHN_CPMISS | B164: Other | C164: Alternative | D164: Alternative - Commodity | E164: -15.00pct | F164: Copper LME 1 USD_COMD_LP_1 - Price Level -15.00 pct,
A165: CHN_CPMISS | B165: Other | C165: Alternative | D165: Alternative - Commodity | E165: -20.00pct | F165: Brent Crude ICE 1 USD_COMD_CO_1 - Price Level -20.00 pct,
A166: CHN_CPMISS | B166: Other | C166: Other | D166: Other - Index | E166: -10.00pct | F166: MSCI China MS_CN_LCL - Index Level -10.00 pct
A167: CHN_CPMISS | B167: Other | C167: Time | D167: Time | E167: 30.00days | F167: Time ALL_TIME - Time 30.00 days,
A168: CHN_CPMISS | B168: Spread | C168: Spread | D168: Corporate HY USD - Industry | E168: 50.00bps | F168: China Corp HY USD_CN_CORP_HY - Spread Yield 50.00 bps,
A169: CHN_CPMISS | B169: Term Structure | C169: Curve (Local) | D169: Govt Emerging Markets | E169: -10.00bps | F169: CNY 2Y CNY_2yr - Yield -10.00 bps,
A170: CHN_CPMISS | B170: Term Structure | C170: Curve (Local) | D170: Govt Emerging Markets | E170: 20.00bps | F170: CNY 10Y CNY_10yr - Yield 20.00 bps,
... A261: CONF_CHI | B261: Term Structure | C261: Curve (Local) | D261: Govt USD | E261: -20.00bps | F261: Tsy 10Y USD_10yr - Yield -20.00 bps,
A262: CONF_RUS | D262: Corporate HY USD - Country | E262: 100.00bps | F262: Russia USD_EM_CORP_EE_RU - Spread Yield 100.00 bps
A263: CONF_RUS | B263: Equity | C263: Equity Derivatives | D263: Equity Implied Volatility | E263: 10.00pct | F263: VIX VIX - Index Level 10.00 pct,
A264: CONF_RUS | B264: Equity | C264: Equity Derivatives | D264: Equity Implied Volatility | E264: -10.00pct | F264: MSCI World Net TR MSCIWLDNET - Index Level -10.00 pct,
A265: CONF_RUS | B265: Equity | C265: Equity Derivatives | D265: Equity Implied Volatility | E265: -25.00pct | F265: Russia RTS RTSI - Index Level -25.00 pct,
A266: CONF_RUS | B266: FX | C266: FX | D266: Emerging Currency | E266: -20.00pct | F266: RUB/USD RUB_FX_USD - FX -20.00 pct,
A267: CONF_RUS | B267: Spread | C267: Spread | D267: Spread Emerging Markets - Country | E267: 100.00bps | F267: Russia USD_EM_DS_RUSSIA - Spread Yield 100.00 bps,
A268: CONF_RUS | B268: Spread | C268: Spread | D268: Spread Emerging Markets - Country | E268: 25.00bps | F268: EMBIG DxS USD_EM_DS_G - Spread Yield 25.00 bps,
A269: CONF_RUS | B269: Term Structure | C269: Curve (Local) | D269: Govt USD | E269: -20.00bps | F269: Tsy 10Y USD_10yr - Yield -20.00 bps,
A270: CONF_TER | B270: Equity | C270: Equity Derivatives | D270: Equity Implied Volatility | E270: -10.00pct | F270: MSCI World Net TR MSCIWLDNET - Index Level -10.00 pct,
A271: CONF_TER | B271: Equity | C271: Equity Derivatives | D271: Equity Implied Volatility | E271: 20.00pct | F271: VIX VIX - Index Level 20.00 pct,
A272: CONF_TER | B272: Other | C272: Alternative | D272: Alternative - Commodity | E272: 10.00pct | F272: Gold COMEX 1 USD_COMD_GC_1 - Price Level 10.00 pct,
A273: CONF_TER | B273: Other | C273: Index Level | D273: Dollar Index | E273: 3.00pct | F273: DXY DXY - Index Level 3.00 pct,
A274: CONF_TER | B274: Spread | C274: Spread | D274: Corporate HY USD - CDX | E274: 80.00bps | F274: CDX.NA.HY.5 USD_CORP_HY_5YN - Spread Yield 80.00 bps
... A314: COVID_V | B314: Term Structure | C314: Curve (Local) | D314: Govt USD | E314: 25.00bps | F314: Tsy 30Y - Tsy 2Y [USD_30yr-USD_2yr] - Yield 25.00 bps,
A315: CRASH08 | D315: - | E315: (blank) | F315: -
A316: CREDIT07 | D316: - | E316: (blank) | F316: -
A317: CVIRUS_GC | B317: Equity | C317: Equity Derivatives | D317: Equity Implied Volatility | E317: -8.00 pct | F317: MSCI World Net TR MSCIWLDNET - Index Level -8.00 pct,
A318: CVIRUS_GC | B318: Equity | C318: Industry Allocation | D318: Consumer Discretionary | E318: -4.00 pct | F318: Consumer Services FMI_WRLD_CDICONSVCS - Industry Return -4.00 pct,
A319: CVIRUS_GC | B319: Equity | C319: Industry Allocation | D319: Consumer Discretionary | E319: -4.50 pct | F319: Textiles Apparel Luxury Goods FMI_WRLD_CDITXTLUX - Industry Return -4.50 pct,
A320: CVIRUS_GC | B320: Equity | C320: Industry Allocation | D320: Industrials | E320: -4.00 pct | F320: Transportation FMI_WRLD_INDTRAN - Industry Return -4.00 pct,
A321: CVIRUS_GC | B321: FX | C321: FX | D321: Developed Currency | E321: 2.00 pct | F321: CHF/USD CHF_FX_USD - FX 2.00 pct,
A322: CVIRUS_GC | B322: FX | C322: FX | D322: Emerging Currency | E322: -3.00 pct | F322: TWD/USD TWD_FX_USD - FX -3.00 pct,
A323: CVIRUS_GC | B323: FX | C323: FX | D323: Emerging Currency | E323: -3.50 pct | F323: CNY/USD CNY_FX_USD - FX -3.50 pct,
A324: CVIRUS_GC | B324: FX | C324: FX | D324: JPY | E324: 3.00 pct | F324: JPY/USD JPY_FX_USD - FX 3.00 pct,
A325: CVIRUS_GC | B325: Other | C325: Alternative | D325: Alternative - Commodity | E325: -10.00 pct | F325: Brent Crude ICE 1 USD_COMD_CO_1 - Price Level -10.00 pct,
A326: CVIRUS_GC | B326: Other | C326: Alternative | D326: Alternative - Commodity | E326: 6.00 pct | F326: Gold COMEX 1 USD_COMD_GC_1 - Price Level 6.00 pct,
A327: CVIRUS_GC | B327: Other | C327: Other | D327: Other - Index | E327: -15.00 pct | F327: MSCI China MS_CN_LCL - Index Level -15.00 pct,
A328: CVIRUS_GC | B328: Other | C328: Other | D328: Other - Index | E328: -5.00 pct | F328: MSCI Japan - MSCI EUROPE(EUR) [MS_JP-MXEU] - Index Level -5.00 pct
... A755: FED_STAY | B755: Term Structure | C755: Curve (Local) | D755: Govt USD | E755: 35.00 bps | F755: Tsy 2Y USD_2yr - Yield 35.00 bps,
A756: FED13_ABS | D756: - | E756: (blank) | F756: -
A757: FEDTAP13 | D757: - | E757: (blank) | F757: -
A758: FISC_NO | B758: FX | C758: FX | D758: EUR | E758: -2.00 pct | F758: EUR/USD EUR_FX_USD - FX -2.00 pct,
A759: FISC_NO | B759: Other | C759: Other | D759: Other - Index | E759: 5.00 pct | F759: MSCI World Utilities - MSCI World IT [MSUTIL_LCL-MSIT_LCL] - Index Level 5.00 pct,
A760: FISC_NO | B760: Spread | C760: Spread | D760: Corporate HY USD - Industry | E760: 25.00 bps | F760: China Corp HY - India Corp HY [USD_CN_CORP_HY-USD_IN_CORP_HY] - Spread Yield 25.00 bps,
A761: FISC_NO | B761: Spread | C761: Spread | D761: Corporate IG USD - Other | E761: -15.00 bps | F761: US Cash Bonds HY - US Cash Bonds IG [USD_LEH_HY3-USD_LEH_CREDIT3] - Spread Yield -15.00 bps
A762: FISC_NO | B762: Spread | C762: Spread | D762: Corporate IG USD - Other | E762: -35.00 bps | F762: US Cash Bonds HY USD_LEH_HY3 - Spread Yield -35.00 bps,
A763: FISC_NO | B763: Spread | C763: Spread | D763: Spread Emerging Markets - Country | E763: -20.00 bps | F763: EMBIG DxS USD_EM_DS_G - Spread Yield -20.00 bps,
A764: FISC_NO | B764: Term Structure | C764: Curve (Local) | D764: Govt EUR (Ger) | E764: -10.00 bps | F764: DEM 2Y EUR_2yr - Yield -10.00 bps,
A765: FISC_NO | B765: Term Structure | C765: Curve (Local) | D765: Govt EUR (Ger) | E765: -20.00 bps | F765: DEM 10Y EUR_10yr - Yield -20.00 bps,
A766: FISC_NO | B766: Term Structure | C766: Curve (Local) | D766: Govt USD | E766: -15.00 bps | F766: Tsy 10Y USD_10yr - Yield -15.00 bps,
A767: FISC_NO | B767: Term Structure | C767: Curve (Local) | D767: Govt USD | E767: -5.00 bps | F767: Tsy 2Y USD_2yr - Yield -5.00 bps,
A768: FISC_SUC | B768: Equity | C768: Equity Derivatives | D768: Equity Implied Volatility | E768: 4.00 pct | F768: MSCI World Net TR MSCIWLDNET - Index Level 4.00 pct,
A769: FISC_SUC | B769: FX | C769: FX | D769: EUR | E769: -2.00 pct | F769: EUR/USD EUR_FX_USD - FX -2.00 pct,
...

Sheet Mapping DEF
A1: Mapping 3 livello | B1: Mapping 2 livello | C1: Mapping 1 Livello
A2: Govt USD | B2: Curve (Local) | C2: Term Structure
A3: Equity Implied Volatility | B3: Equity Derivatives | C3: Equity
A4: Alternative - Commodity | B4: Alternative | C4: Other
A5: Emerging Currency | B5: FX | C5: FX
A6: Industrials | B6: Industry Allocation | C6: Equity
A7: Information Technology | B7: Industry Allocation | C7: Equity
A8: Corporate HY USD - Industry | B8: Spread | C8: Spread
A9: USD Inflation | B9: Inflation | C9: Other
A10: Govt EUR (Ger) | B10: Curve (Local) | C10: Term Structure
A11: Govt Developed Other (AU, GB, JP, ...) | B11: Curve (Local) | C11: Term Structure
A12: JPY | B12: FX | C12: FX
... A71: Corporate HY USD - Maturity | B71: Spread | C71: Spread
